CMD/wrapper_serial_paralelo/wrapper_serial_paralelo.v
module wrapper_serial_paralelo (parallel, serial, sd_clock, enable, reset, complete);
	

	input enable;
	input serial;
	input reset;
	input sd_clock;
	//input [7:0]framesize

	output [n-1:0] parallel;
	output         complete;

	wire enable;
	wire serial;
	wire reset;
	wire sd_clock;
	//wire [7:0]framesize

	reg [n-1:0] parallel;
	reg         complete;

	integer count = 0;
	parameter n = 7;	
	
	always @ (posedge sd_clock)
		begin
			if (reset) begin
				parallel [n-1:0] <= 0;
			end else begin
				if (enable) begin
					parallel [n-1-count] <= serial;
				end else begin
					 parallel <= parallel;
				end
			end
		end
	
	always @ (negedge sd_clock)
		begin
			if(enable) begin
				if(count != n-1) begin
					count = (count + 1);
				end else begin
					count = 0;
				end 
			end	
		end
	
	always @ (posedge sd_clock)
		begin
			if (count == n-1) begin
				complete = 1'b1;
			end else begin
				complete = 1'b0;
			end
		end	

endmodule

CMD/wrapper_serial_paralelo/probador.v
`timescale 1 ns / 1 ps

module probador (input_1, clk, enable, reset);

	output reg input_1;
	output reg clk;
	output reg enable;
	output reg reset;	           


   initial begin
      enable = 1;
      reset = 0;
      clk = 0;
      input_1 = 0;  
      
      
     #2 input_1 = 1;
     #2 input_1 = 1;
     #2 input_1 = 1;
     #2 input_1 = 1;
     #2 input_1 = 1;
     #2 input_1 = 1;
     #2 input_1 = 1;
     #2 input_1 = 1;
     #2 input_1 = 0;
     #2 input_1 = 0;
     #2 input_1 = 0;
     #2 input_1 = 0;
     #2 input_1 = 1;
     #2 input_1 = 1;
     #2 input_1 = 1;
     #2 input_1 = 1;

     #5 $finish;
   end

   always #1 clk = !clk;

endmodule // probador

CMD/wrapper_serial_paralelo/testbench.v
module testbench;    

	parameter n = 7; //paralell signal size at output
	wire input_1;
	wire clk;
	wire enable;
	wire reset;
	wire [n-1:0] output_n;
	wire push;

  initial begin          
     $dumpfile("testbench.vcd");     
     $dumpvars(0,testbench);
  end
       

  probador valores (input_1, clk, enable, reset);

  wrapper_serial_paralelo c1 (output_n, input_1, clk, enable, reset, push); 
   

endmodule

CMD/wrapper_serial_paralelo/testbench.vcd
$date
	Fri Dec  9 01:57:50 2016
$end
$version
	Icarus Verilog
$end
$timescale
	1ps
$end
$scope module testbench $end
$var wire 1 ! reset $end
$var wire 1 " push $end
$var wire 7 # output_n [6:0] $end
$var wire 1 $ input_1 $end
$var wire 1 % enable $end
$var wire 1 & clk $end
$scope module c1 $end
$var wire 1 $ serial $end
$var wire 1 & sd_clock $end
$var wire 1 ! reset $end
$var wire 1 % enable $end
$var reg 1 " complete $end
$var reg 7 ' parallel [6:0] $end
$var integer 32 ( count [31:0] $end
$upscope $end
$scope module valores $end
$var reg 1 & clk $end
$var reg 1 % enable $end
$var reg 1 $ input_1 $end
$var reg 1 ! reset $end
$upscope $end
$upscope $end
$enddefinitions $end
#0
$dumpvars
b0 (
bx '
0&
1%
0$
bx #
x"
0!
$end
#1000
b0xxxxxx #
b0xxxxxx '
0"
1&
#2000
b1 (
0&
1$
#3000
b1xxxxx #
b1xxxxx '
1&
#4000
b10 (
0&
#5000
b11xxxx #
b11xxxx '
1&
#6000
b11 (
0&
#7000
b111xxx #
b111xxx '
1&
#8000
b100 (
0&
#9000
b1111xx #
b1111xx '
1&
#10000
b101 (
0&
#11000
b11111x #
b11111x '
1&
#12000
b110 (
0&
#13000
b111111 #
b111111 '
1"
1&
#14000
b0 (
0&
#15000
b1111111 #
b1111111 '
0"
1&
#16000
b1 (
0&
#17000
1&
#18000
b10 (
0&
0$
#19000
b1101111 #
b1101111 '
1&
#20000
b11 (
0&
#21000
b1100111 #
b1100111 '
1&
#22000
b100 (
0&
#23000
b1100011 #
b1100011 '
1&
#24000
b101 (
0&
#25000
b1100001 #
b1100001 '
1&
#26000
b110 (
0&
1$
#27000
1"
1&
#28000
b0 (
0&
#29000
0"
1&
#30000
b1 (
0&
#31000
1&
#32000
b10 (
0&
#33000
b1110001 #
b1110001 '
1&
#34000
b11 (
0&
#35000
b1111001 #
b1111001 '
1&
#36000
b100 (
0&
#37000
b1111101 #
b1111101 '
1&
