TransicionEstados.v
module TransicionEstados(EstadoActual, End, Valid, Tran,  Data_Transfer, STOP, Command_Reg_Write_or_Continue, ProximoEstado, ADMA_Error_Interrupt, ENB);
//Módulo util para la transición de estados. 
//End, Valid y Tran provienen del descriptor line, así que son entradas
//TFC es una bandera
//ADMA Error Interrupt es una señal de salida
//ENB es una señal que habilita la transición de estados

//Hace falta incluir los registros

  output [1:0] ProximoEstado; 
  output       ADMA_Error_Interrupt;
  input  [1:0] EstadoActual;
  input        End, Valid, Tran,  ENB, Data_Transfer,STOP, Command_Reg_Write_or_Continue;


  reg TFC;                                    //verrrrrrrrrrrrrrrrrrrrr
  reg  [1:0]  ProximoEstado;
  reg         ADMA_Error_Interrupt=0;
  wire [1:0]  EstadoActual;
  wire        End, Valid, Tran, ENB, Data_Transfer,STOP, Command_Reg_Write_or_Continue;


//ESTADO 00= ST_FDS
//ESTADO 01= ST_CADR 
//ESTADO 10= ST_TFR
//ESTADO 11= ST_STOP


always @(*)
      case(EstadoActual)
      00:                             
        if(Valid==1)begin
		ProximoEstado <= 01;
		ADMA_Error_Interrupt <= 0;
		end
	else begin
		ProximoEstado<= 00;
		ADMA_Error_Interrupt <= 1;
		TFC=0;
	     end
      01:  
        if (Tran==1) begin
		ProximoEstado <= 02;
		ADMA_Error_Interrupt<=0;
		     end        
	else begin
		if(End==1) begin
			ProximoEstado<= 03;
			ADMA_Error_Interrupt<=0;
		           end		
		else begin
			ProximoEstado<= 00;
			ADMA_Error_Interrupt<=0;
		     end
	     end      
	02:  
        if (Data_Transfer==1) begin                 //Data_Transfer=1 si aún estoy transmitiendo información
		ProximoEstado <= 02;
		ADMA_Error_Interrupt<=0;
		TFC=1;
		end
        else begin
		if((TFC==1)&((End==1)|(STOP==1))) begin
			ProximoEstado <= 03;
			ADMA_Error_Interrupt<=0;
		                                  end
		else begin
			if((TFC==1)&((End==0)&(STOP==0))) begin
			ProximoEstado <= 00;
			ADMA_Error_Interrupt<=0;
							  end	
		     end
            end      
	03:
	if (Command_Reg_Write_or_Continue==1) begin
		ProximoEstado <= 00;
		ADMA_Error_Interrupt<=0;
		                              end
	else begin
		ProximoEstado <= 03;
		ADMA_Error_Interrupt<=0;
             end

      default: begin
		 ProximoEstado <= EstadoActual;
	         ADMA_Error_Interrupt<=0;
		end
      endcase

		

endmodule

Probador.v
`timescale 1 ns / 1 ps
module probador(EstadoActual, End, Valid, Tran, Data_Transfer, STOP, Command_Reg_Write_or_Continue, ENB);


output [1:0] EstadoActual;
output       End, Valid, Tran, TFC,Data_Transfer,STOP, Command_Reg_Write_or_Continue, ENB;

reg [1:0] EstadoActual;
reg       End, Valid, Tran, TFC,Data_Transfer,STOP, Command_Reg_Write_or_Continue, ENB;

initial begin
   EstadoActual = 2'b00;
   End = 0;
   Valid = 1;
   Tran = 0;
   Data_Transfer = 1;
   STOP = 0;
   Command_Reg_Write_or_Continue= 1;
   ENB = 0;
   #1000 $finish;

   end

   always #100 ENB <= !ENB;
   always #249  EstadoActual<= EstadoActual+1;
   always #50  End <= !End;
   always #50  Valid <= !Valid;
   always #50  Tran <= !Tran;
   always #50  Data_Transfer <= !Data_Transfer;
   always #50  STOP <= !STOP;
   always #50  Command_Reg_Write_or_Continue<= !Command_Reg_Write_or_Continue;  

endmodule

TestBench.v
module test;

 wire [1:0] EstadoActual;
 wire End;
 wire Valid;
 wire Tran;

 wire Data_Transfer;
 wire STOP;
 wire Command_Reg_Write_or_Continue;
 wire [1:0] ProximoEstado;
 wire ADMA_Error_Interrupt;
 wire ENB;

   initial begin
      $dumpfile("test.vcd");
      $dumpvars(0,test);
   end

   probador senales (EstadoActual, End, Valid, Tran, Data_Transfer, STOP, Command_Reg_Write_or_Continue, ENB);

   TransicionEstados transicion (EstadoActual, End, Valid, Tran, Data_Transfer, STOP, Command_Reg_Write_or_Continue, ProximoEstado, ADMA_Error_Interrupt, ENB);

endmodule

test.vcd
$date
	Wed Nov  2 16:49:19 2016
$end
$version
	Icarus Verilog
$end
$timescale
	1ps
$end
$scope module test $end
$var wire 1 ! Valid $end
$var wire 1 " Tran $end
$var wire 1 # STOP $end
$var wire 2 $ ProximoEstado [1:0] $end
$var wire 2 % EstadoActual [1:0] $end
$var wire 1 & End $end
$var wire 1 ' ENB $end
$var wire 1 ( Data_Transfer $end
$var wire 1 ) Command_Reg_Write_or_Continue $end
$var wire 1 * ADMA_Error_Interrupt $end
$scope module senales $end
$var reg 1 ) Command_Reg_Write_or_Continue $end
$var reg 1 ( Data_Transfer $end
$var reg 1 ' ENB $end
$var reg 1 & End $end
$var reg 2 + EstadoActual [1:0] $end
$var reg 1 # STOP $end
$var reg 1 , TFC $end
$var reg 1 " Tran $end
$var reg 1 ! Valid $end
$upscope $end
$scope module transicion $end
$var wire 1 ) Command_Reg_Write_or_Continue $end
$var wire 1 ( Data_Transfer $end
$var wire 1 ' ENB $end
$var wire 1 & End $end
$var wire 2 - EstadoActual [1:0] $end
$var wire 1 # STOP $end
$var wire 1 " Tran $end
$var wire 1 ! Valid $end
$var reg 1 * ADMA_Error_Interrupt $end
$var reg 2 . ProximoEstado [1:0] $end
$var reg 1 / TFC $end
$upscope $end
$upscope $end
$enddefinitions $end
#0
$dumpvars
x/
b1 .
b0 -
x,
b0 +
0*
1)
1(
0'
0&
b0 %
b1 $
0#
0"
1!
$end
#50000
1*
b0 $
b0 .
0/
0)
1#
0(
1"
0!
1&
#100000
0*
b1 $
b1 .
1)
0#
1(
0"
1!
0&
1'
#150000
1*
b0 $
b0 .
0)
1#
0(
1"
0!
1&
#200000
0*
b1 $
b1 .
1)
0#
1(
0"
1!
0&
0'
#249000
b0 $
b0 .
b1 %
b1 +
b1 -
#250000
b10 $
b10 .
0)
1#
0(
1"
0!
1&
#300000
b0 $
b0 .
1)
0#
1(
0"
1!
0&
1'
#350000
b10 $
b10 .
0)
1#
0(
1"
0!
1&
#400000
b0 $
b0 .
1)
0#
1(
0"
1!
0&
0'
#450000
b10 $
b10 .
0)
1#
0(
1"
0!
1&
#498000
b10 %
b10 +
b10 -
#500000
1/
1)
0#
1(
0"
1!
0&
1'
#550000
b11 $
b11 .
0)
1#
0(
1"
0!
1&
#600000
b10 $
b10 .
1)
0#
1(
0"
1!
0&
0'
#650000
b11 $
b11 .
0)
1#
0(
1"
0!
1&
#700000
b10 $
b10 .
1)
0#
1(
0"
1!
0&
1'
#747000
b0 $
b0 .
b11 %
b11 +
b11 -
#750000
b11 $
b11 .
0)
1#
0(
1"
0!
1&
#800000
b0 $
b0 .
1)
0#
1(
0"
1!
0&
0'
#850000
b11 $
b11 .
0)
1#
0(
1"
0!
1&
#900000
b0 $
b0 .
1)
0#
1(
0"
1!
0&
1'
#950000
b11 $
b11 .
0)
1#
0(
1"
0!
1&
#996000
1*
b0 $
b0 .
0/
b0 %
b0 +
b0 -
#1000000
0*
b1 $
b1 .
1)
0#
1(
0"
1!
0&
0'
