CMD/capa_fisica/pad.v
module pad(output_input, enable, data_in, data_out, sd_clock, i_port, o_port);

   
	input output_input;	// salida (1) o entrada (0) (CCF)
	input enable;		// Habilitacion	(CCF)
	input data_in;		// Datos por enviar (wrapper P-S)
	input sd_clock;		// Reloj de la tarjeta SD
	input i_port;		// Linea de la tarjeta SD (SD)

	output data_out;	// Datos recibidos (wrapper S-P)
	output o_port;		// Linea hacia la tarjeta SD (SD)


	wire output_input;
	wire enable;
	wire data_in;
	wire sd_clock;
	wire i_port;

	reg data_out;
	reg o_port;

   
	always @(posedge sd_clock) begin
		if (enable) begin
			if (output_input == 1) begin
				o_port <= data_in;
				data_out <= 1'bz;
			end else begin
				o_port <= 1'bz;
				data_out <= i_port;
			end
		end else begin
			o_port <= 1'bz;
			data_out <= 1'bz;
		end
	end					

endmodule

CMD/capa_fisica/wrapper_serial_paralelo.v
module wrapper_serial_paralelo (parallel, serial, sd_clock, enable, reset, complete);
	

	input enable;
	input serial;
	input reset;
	input sd_clock;
	//input [7:0]framesize

	output [n-1:0] parallel;
	output         complete;

	wire enable;
	wire serial;
	wire reset;
	wire sd_clock;
	//wire [7:0]framesize

	reg [n-1:0] parallel;
	reg         complete;

	integer count = 0;
	parameter n = 7;	
	
	always @ (posedge sd_clock)
		begin
			if (reset) begin
				parallel [n-1:0] <= 0;
			end else begin
				if (enable) begin
					parallel [n-1-count] <= serial;
				end else begin
					 parallel <= parallel;
				end
			end
		end
	
	always @ (posedge sd_clock)
		begin
			if(enable) begin
				if(count != n-1) begin
					count = (count + 1);
				end else begin
					count = 0;
				end 
			end	
		end
	
	always @ (posedge sd_clock)
		begin
			if (count == n-1) begin
				complete = 1'b1;
			end else begin
				complete = 1'b0;
			end
		end	

endmodule

CMD/wrapper_paralelo_serial/wrapper_paralelo_serial.v
module wrapper_paralelo_serial (enable, parallel, serial, complete, reset, sd_clock, load_send);
	
	
	input           enable;			// Habilitacion de la carga (CCF)
	input           load_send;		// Enviar (1) cargar (0) (CCF)
	input [n-1 : 0] parallel;		// Trama por enviar (CMD)
	input           reset;
	input           sd_clock;

	output serial;				// Salida serializada (PAD)
	output complete;			// Transmision completa (CCF)

	wire           enable;
	wire           load_send;
	wire [n-1 : 0] parallel;
	wire           reset;
	wire           sd_clock;

	reg serial;
	reg complete;
	reg next_complete;

	integer count = 0;		
	parameter n = 48;
	reg [n-1 : 0] parallel_cargado;


	always @ (posedge sd_clock)
		begin
			if (reset) begin
				serial <= 0;
				parallel_cargado <= 0;
			end else begin
				if (enable) begin
					parallel_cargado <= parallel;
				end else begin
					parallel_cargado <= parallel_cargado;
				end
				if (load_send) begin
					serial <= parallel_cargado [n-1-count];
				end else begin
					 serial <= serial;
				end
			end
		end
	
	always @ (negedge sd_clock)
		begin
			if(reset) begin
				count <= 0;
			end else begin
				if(load_send) begin
					if(count != n-1) begin
						count <= (count + 1);
					end else begin
						count <= 0;
					end 
				end	
			end
		end
	//complete signal generation
	always @ (posedge sd_clock)
		begin
			if (count == n-1) begin
				next_complete = 1'b1;
			end else begin
				next_complete = 1'b0;
			end
		end

	always @ (negedge sd_clock) begin
		complete <= next_complete;
	end

endmodule

CMD/CMD/control_capa_fisica.v

module control_capa_fisica(strobe_in, ack_in, idle_in, no_response, pad_response, reception_complete, transmission_complete, ack_out, strobe_out, response, command_timeout, load_send, enable_pts_wrapper, enable_stp_wrapper, pad_state, pad_enable, reset, sd_clock, reset_wrapper);


   input           strobe_in;				// Solicitud de servicio (CMD)
   input           ack_in;				// Sincronizacion (CMD)
   input           idle_in;				// Ir al estado Idle (CMD)
   input           no_response;				// No esperar una respuesta (interna)
   input [14 : 0] pad_response;			// Trama recibida (wrapper S-P)
   input 	   reception_complete;			// Recepcion completa (wrapper S-P)
   input 	   transmission_complete;		// Transmision completa (wrapper P-S)
   input 	   reset;				// Reinicio
   input 	   sd_clock;				// reloj (Tarjeta SD)

   output 	    ack_out;				// Sincronizacion (CMD)
   output 	    strobe_out;				// Proceso concluido (CMD)
   output [14 : 0] response;				// trama recibida (CMD)
   output 	    command_timeout;			// Ocurrencia del timeout (CMD-Regs)
   output 	    load_send;				// Enviar o cargar (P-S)
   output 	    enable_pts_wrapper;			// Habilitar paralelo a serie (wrapper P-S)
   output 	    enable_stp_wrapper;			// Habilitar serie a paralelo (Wrapper S- P)
   output           reset_wrapper;			// Reinicia los wrappers ( ambos wrappers)
   output 	    pad_state;				// Salida (1) o entrada (0) (PAD)
   output	    pad_enable;				// Habilita el Pad (PAD)

  // inout            cmd_pin;


   wire           strobe_in;
   wire           ack_in;
   wire           idle_in;
   wire           no_response;
   wire [14 : 0] pad_response;
   wire 	  reception_complete;
   wire 	  transmission_complete;
   wire 	  reset;
   wire 	  sd_clock;

   reg  	 ack_out;
   reg 	         strobe_out;
   reg [14 : 0] response;
   reg   	 command_timeout;
   reg 	         load_send;
   reg		 reset_wrapper;
   reg 	         enable_pts_wrapper;
   reg 	         enable_stp_wrapper;
   reg 	         pad_state;
   reg	         pad_enable;

   //reg           cmd_pin;

   reg [7:0] 	 state = 8'b00000001;
   reg [7:0] 	 next_state ; 		 

   integer count = 0;
   reg problem = 0;
   reg prueba = 0;
   reg reset_wrapper_2 = 0;
   reg enable_stp_wrapper_2 = 0;

   parameter reset_state = 8'b00000001;
   parameter idle = 8'b00000010;
   parameter load_command = 8'b00000100;
   parameter send_command = 8'b00001000;
   parameter wait_response = 8'b00010000;
   parameter send_response = 8'b00100000;
   parameter wait_ack = 8'b01000000;
   parameter send_ack = 8'b10000000;

   always @(posedge sd_clock) begin
   state <= next_state; 
   end



   always @(*) begin

      case(state)

	reset_state:
	  begin
	     ack_out                <= 0;
	     strobe_out             <= 0;
	     response [14 : 0]     <= 0;
             command_timeout        <= 0;
	     load_send              <= 0;
	     enable_pts_wrapper     <= 0;
	     enable_stp_wrapper     <= 0;
	     reset_wrapper          <= 0;
	     pad_state              <= 0;
	     pad_enable             <= 0;

	     next_state <= idle;
	  end // case: reset_state

	idle:
	  begin
	     reset_wrapper_2 <= 1;

	     if (idle_in == 1) begin
		next_state <= idle;
	     end else begin
		if (strobe_in == 1) begin
	 	   next_state <= load_command;
	        end else begin
		   next_state <= idle;
	        end
	     end 
	  end // case: idle

	load_command:
	  begin
	     enable_pts_wrapper <= 1;
	     pad_state <= 1;
	     pad_enable <= 1;

	     if(idle_in == 1) begin
		next_state <= idle;
	     end else begin
		prueba <= 1;
	     end

	  end // case: load_command

	send_command:
	  begin
	     load_send <= 1;

	     if (idle_in == 1) begin
		next_state <= idle;
	     end else begin
		if (transmission_complete == 1) begin
		   next_state <= wait_response;
		end else begin
		   next_state <= send_command;
		end
	     end

	  end // case: send_command

	wait_response:
	  begin
	     pad_enable <= 0;
	     enable_stp_wrapper_2 <= 1;          // implementar contador interno

	     if (problem == 1) begin
		command_timeout <= 1;
	     end else begin
		command_timeout <= 0;
	     end

	     if (idle_in == 1) begin
		next_state <= idle;
	     end else begin
		if (reception_complete == 1 || no_response == 1) begin
		   next_state <= send_response;
		end else begin
		   next_state <= wait_response;
		end
	     end
	     

	  end // case: wait_response

	send_response:
	  begin
	     strobe_out <= 1;
	     response <= pad_response;

	     if (idle_in == 1) begin
		next_state <= idle;
	     end else begin
		next_state <= wait_ack;
	     end
	  end // case: send_response
	

       wait_ack:                        
	 begin

	     ack_out                <= 0;
	     strobe_out             <= 0;
	     response [14 : 0]     <= 0;
             command_timeout        <= 0;
	     load_send              <= 0;
	     enable_pts_wrapper     <= 0;
	     enable_stp_wrapper     <= 0;
	     reset_wrapper          <= 0;
	     pad_state              <= 0;
	     pad_enable             <= 0;

	    if (idle_in == 1) begin
	       next_state <= idle;
	    end else begin
	       if (ack_in == 1) begin
		  next_state <= send_ack;
	       end else begin
		  next_state <= wait_ack;
	       end
	    end

	 end // case: wait_ack
	

	send_ack:
	  begin
	     ack_out <= 1;
	     next_state <= idle;
	  end
	
      endcase // case (state)
      

      end // always @ (posedge clock)


	always @ (negedge sd_clock)
		begin
			if(state != 8'b00010000) begin
				count <= 0;
				problem <= 0;
			end else begin
				if(count != 136) begin
					count <= (count + 1);
				end else begin
					count <= 0;
					problem <= 1;
				end 	
			end
		end

	always @ (posedge sd_clock) begin
		if(state == load_command && prueba == 1) begin
			next_state <= send_command;
		end else begin
			next_state <= next_state;
		end
	end

	always @ (negedge sd_clock) begin
		if(state == idle && reset_wrapper_2 == 1) begin
			reset_wrapper <= 1;
		end else begin
			reset_wrapper <= 0;
		end
	end

	always @ (posedge sd_clock) begin
		if(state == wait_response && enable_stp_wrapper_2 == 1) begin
			enable_stp_wrapper <= 1;
		end else begin
			enable_stp_wrapper <= enable_stp_wrapper;
		end
	end


endmodule

CMD/CMD/capa_fisica.v
`include "control_capa_fisica.v"
`include "wrapper_paralelo_serial.v"
`include "wrapper_serial_paralelo.v"
`include "pad.v"

module capa_fisica(strobe_in, ack_in, idle_in, cmd_to_send, ack_out, strobe_out, no_response, response, command_timeout, reset, sd_clock, cmd_pin_in, cmd_pin_out);


   input          strobe_in;
   input          ack_in;
   input          idle_in;
   input [39 : 0] cmd_to_send;
   input          reset;
   input 	  sd_clock;
   input	  cmd_pin_in;


   output 	   ack_out;
   output 	   strobe_out;
   input          no_response;
   output [14 : 0] response;
   output 	   command_timeout;
   output	   cmd_pin_out;



   wire          strobe_in;
   wire          ack_in;
   wire          idle_in;
   wire [39 : 0] cmd_to_send;
   wire          reset;
   wire 	 sd_clock;
   wire		 cmd_pin_in;


   wire           ack_out;
   wire 	          strobe_out;
   reg            serial_ready;
   wire [14 : 0 ] response;
   wire 	          command_timeout;
   wire		  cmd_pin_out;


   wire 	  enable_pts_wrapper;
   wire 	  enable_stp_wrapper;
   wire [14 : 0 ] pad_response;
   wire 	  reception_complete;
   wire 	  transmission_complete;
   wire		  load_send;
   wire		  pad_state;
   wire 	  pad_enable;
   wire		  reset_wrapper;
   wire		  data_in;
   wire  	  data_out;


   control_capa_fisica control1(	.strobe_in(strobe_in),
					.ack_in(ack_in),
					.idle_in(idle_in),
					//.no_response(),
					.pad_response(pad_response),
					.reception_complete(reception_complete),
					.transmission_complete(transmission_complete),
					.ack_out(ack_out),
					.strobe_out(strobe_out),
					.response(response),
					.command_timeout(command_timeout),
					.load_send(load_send),
					.enable_pts_wrapper(enable_pts_wrapper),
					.enable_stp_wrapper(enable_stp_wrapper),
					.pad_state(pad_state),
					.pad_enable(pad_enable),
					.reset(reset),
					.sd_clock(sd_clock),
					.reset_wrapper(reset_wrapper)
					);

   wrapper_paralelo_serial PTS1(	.enable(enable_pts_wrapper),
					.parallel(cmd_to_send),
					.serial(data_in),
					.complete(transmission_complete),
					.reset(reset_wrapper),
					.sd_clock(sd_clock),
					.load_send(load_send)
					);

   wrapper_serial_paralelo STP1(	.parallel(pad_response),
					.serial(data_out),
					.sd_clock(sd_clock),
					.enable(enable_stp_wrapper),
					.reset(reset_wrapper),
					.complete(reception_complete)
					);

   pad pad1 (				.output_input(pad_enable),
					.enable(pad_state),
					.data_in(data_in),
					.data_out(data_out),
					.sd_clock(sd_clock),
					.i_port(cmd_pin_in),
					.o_port(cmd_pin_out)
					);
 

endmodule

CMD/capa_fisica/probador.v
`timescale 1 ns / 1 ps

module probador (strobe_in, ack_in, idle_in, cmd_to_send, no_response, reset, sd_clock, cmd_pin_in);

   output           strobe_in;
   output           ack_in;
   output           idle_in;
   output           no_response;
   output [39 : 0]  cmd_to_send;
   output 	    cmd_pin_in;
   output 	    reset;
   output 	    sd_clock;

   reg           strobe_in;
   reg           ack_in;
   reg           idle_in;
   reg           no_response;
   reg [39 : 0]  cmd_to_send;
   reg 	         cmd_pin_in;
   reg 	         reset;
   reg 	         sd_clock;             


   initial begin
      no_response = 0;
      cmd_to_send = 40'b11110000_11110000_11110000_11110000_11110000;
      reset = 0;
      sd_clock = 0;
      strobe_in = 0;
      ack_in = 0;
      idle_in = 0;
      cmd_pin_in = 0;
      
      
     #30 strobe_in = 1;
     #89 cmd_pin_in = 1;
     #2 cmd_pin_in = 1;
     #2 cmd_pin_in = 1;
     #2 cmd_pin_in = 0;
     #2 cmd_pin_in = 0;
     #2 cmd_pin_in = 0;
     #2 cmd_pin_in = 0;
     #2 cmd_pin_in = 1;
     #2 cmd_pin_in = 1;
     #2 cmd_pin_in = 1;
     #2 cmd_pin_in = 1;
     #2 cmd_pin_in = 0;
     #2 cmd_pin_in = 0;
     #2 cmd_pin_in = 0;
     #2 cmd_pin_in = 0;
     #2 
     #20 ack_in = 1;

     #5 $finish;
   end

   always #1 sd_clock = !sd_clock;

endmodule // probador

CMD/CMD/testbench.v
module testbench;                                // Se define un modulo de prueba

   wire           strobe_in;
   wire           ack_in;
   wire           idle_in;
   wire           no_response;
   wire [39 : 0]  cmd_to_send;
   wire 	  cmd_pin_in;
   wire           reset;
   wire           sd_clock;

   wire  	  ack_out;
   wire 	  strobe_out;
   wire [14 : 0] response;
   wire   	  command_timeout;
   wire           cmd_pin_out;

  initial begin                             // Bloque que se ejecuta al inicio
     $dumpfile("testbench.vcd");                 // El resultado se guarda en test.vcd
     $dumpvars(0,testbench);
  end
       

  probador valores (strobe_in, ack_in, idle_in, cmd_to_send, no_response, reset, sd_clock, cmd_pin_in);

  capa_fisica c1 (strobe_in, ack_in, idle_in, cmd_to_send, ack_out, strobe_out, no_response, response, command_timeout, reset, sd_clock, cmd_pin_in, cmd_pin_out);
   

endmodule // test

CMD/capa_fisica/testbench.vcd
$date
	Wed Nov 30 13:41:01 2016
$end
$version
	Icarus Verilog
$end
$timescale
	1ps
$end
$scope module testbench $end
$var wire 1 ! strobe_out $end
$var wire 1 " strobe_in $end
$var wire 1 # sd_clock $end
$var wire 15 $ response [14:0] $end
$var wire 1 % reset $end
$var wire 1 & no_response $end
$var wire 1 ' idle_in $end
$var wire 1 ( command_timeout $end
$var wire 40 ) cmd_to_send [39:0] $end
$var wire 1 * cmd_pin_out $end
$var wire 1 + cmd_pin_in $end
$var wire 1 , ack_out $end
$var wire 1 - ack_in $end
$scope module c1 $end
$var wire 1 . transmission_complete $end
$var wire 1 ! strobe_out $end
$var wire 1 " strobe_in $end
$var wire 1 # sd_clock $end
$var wire 15 / response [14:0] $end
$var wire 1 0 reset_wrapper $end
$var wire 1 % reset $end
$var wire 1 1 reception_complete $end
$var wire 1 2 pad_state $end
$var wire 15 3 pad_response [14:0] $end
$var wire 1 4 pad_enable $end
$var wire 1 & no_response $end
$var wire 1 5 load_send $end
$var wire 1 ' idle_in $end
$var wire 1 6 enable_stp_wrapper $end
$var wire 1 7 enable_pts_wrapper $end
$var wire 1 8 data_out $end
$var wire 1 9 data_in $end
$var wire 1 ( command_timeout $end
$var wire 40 : cmd_to_send [39:0] $end
$var wire 1 * cmd_pin_out $end
$var wire 1 + cmd_pin_in $end
$var wire 1 , ack_out $end
$var wire 1 - ack_in $end
$scope module PTS1 $end
$var wire 1 # sd_clock $end
$var wire 1 0 reset $end
$var wire 40 ; parallel [39:0] $end
$var wire 1 5 load_send $end
$var wire 1 7 enable $end
$var reg 1 . complete $end
$var reg 1 < next_complete $end
$var reg 40 = parallel_cargado [39:0] $end
$var reg 1 9 serial $end
$var integer 32 > count [31:0] $end
$upscope $end
$scope module STP1 $end
$var wire 1 8 serial $end
$var wire 1 # sd_clock $end
$var wire 1 0 reset $end
$var wire 1 6 enable $end
$var reg 1 1 complete $end
$var reg 15 ? parallel [14:0] $end
$var integer 32 @ count [31:0] $end
$upscope $end
$scope module control1 $end
$var wire 1 A no_response $end
$var wire 15 B pad_response [14:0] $end
$var wire 1 1 reception_complete $end
$var wire 1 . transmission_complete $end
$var wire 1 " strobe_in $end
$var wire 1 # sd_clock $end
$var wire 1 % reset $end
$var wire 1 ' idle_in $end
$var wire 1 - ack_in $end
$var reg 1 , ack_out $end
$var reg 1 ( command_timeout $end
$var reg 1 7 enable_pts_wrapper $end
$var reg 1 6 enable_stp_wrapper $end
$var reg 1 C enable_stp_wrapper_2 $end
$var reg 1 5 load_send $end
$var reg 8 D next_state [7:0] $end
$var reg 1 4 pad_enable $end
$var reg 1 2 pad_state $end
$var reg 1 E problem $end
$var reg 1 F prueba $end
$var reg 1 0 reset_wrapper $end
$var reg 1 G reset_wrapper_2 $end
$var reg 15 H response [14:0] $end
$var reg 8 I state [7:0] $end
$var reg 1 ! strobe_out $end
$var integer 32 J count [31:0] $end
$upscope $end
$scope module pad1 $end
$var wire 1 9 data_in $end
$var wire 1 2 enable $end
$var wire 1 4 output_input $end
$var wire 1 # sd_clock $end
$var wire 1 + i_port $end
$var reg 1 8 data_out $end
$var reg 1 * o_port $end
$upscope $end
$upscope $end
$scope module valores $end
$var reg 1 - ack_in $end
$var reg 1 + cmd_pin_in $end
$var reg 40 K cmd_to_send [39:0] $end
$var reg 1 ' idle_in $end
$var reg 1 & no_response $end
$var reg 1 % reset $end
$var reg 1 # sd_clock $end
$var reg 1 " strobe_in $end
$upscope $end
$upscope $end
$enddefinitions $end
#0
$dumpvars
b1111000011110000111100001111000011110000 K
b0 J
b1 I
b0 H
0G
0F
0E
b10 D
0C
bx B
zA
b0 @
bx ?
b0 >
bx =
x<
b1111000011110000111100001111000011110000 ;
b1111000011110000111100001111000011110000 :
x9
x8
07
06
05
04
bx 3
02
x1
00
b0 /
x.
0-
0,
0+
x*
b1111000011110000111100001111000011110000 )
0(
0'
0&
0%
b0 $
0#
0"
0!
$end
#1000
1G
b10 I
z8
z*
0<
01
1#
#2000
10
0.
0#
#3000
b0 3
b0 ?
b0 B
b0 =
09
1#
#4000
0#
#5000
1#
#6000
0#
#7000
1#
#8000
0#
#9000
1#
#10000
0#
#11000
1#
#12000
0#
#13000
1#
#14000
0#
#15000
1#
#16000
0#
#17000
1#
#18000
0#
#19000
1#
#20000
0#
#21000
1#
#22000
0#
#23000
1#
#24000
0#
#25000
1#
#26000
0#
#27000
1#
#28000
0#
#29000
1#
#30000
b100 D
0#
1"
#31000
1F
14
12
17
b100 I
1#
#32000
00
0#
#33000
b1000 D
b1111000011110000111100001111000011110000 =
0*
1#
#34000
0#
#35000
15
b1000 I
1#
#36000
0#
#37000
19
b1 >
1#
#38000
0#
#39000
1*
b10 >
1#
#40000
0#
#41000
b11 >
1#
#42000
0#
#43000
b100 >
1#
#44000
0#
#45000
09
b101 >
1#
#46000
0#
#47000
0*
b110 >
1#
#48000
0#
#49000
b111 >
1#
#50000
0#
#51000
b1000 >
1#
#52000
0#
#53000
19
b1001 >
1#
#54000
0#
#55000
1*
b1010 >
1#
#56000
0#
#57000
b1011 >
1#
#58000
0#
#59000
b1100 >
1#
#60000
0#
#61000
09
b1101 >
1#
#62000
0#
#63000
0*
b1110 >
1#
#64000
0#
#65000
b1111 >
1#
#66000
0#
#67000
b10000 >
1#
#68000
0#
#69000
19
b10001 >
1#
#70000
0#
#71000
1*
b10010 >
1#
#72000
0#
#73000
b10011 >
1#
#74000
0#
#75000
b10100 >
1#
#76000
0#
#77000
09
b10101 >
1#
#78000
0#
#79000
0*
b10110 >
1#
#80000
0#
#81000
b10111 >
1#
#82000
0#
#83000
b11000 >
1#
#84000
0#
#85000
19
b11001 >
1#
#86000
0#
#87000
1*
b11010 >
1#
#88000
0#
#89000
b11011 >
1#
#90000
0#
#91000
b11100 >
1#
#92000
0#
#93000
09
b11101 >
1#
#94000
0#
#95000
0*
b11110 >
1#
#96000
0#
#97000
b11111 >
1#
#98000
0#
#99000
b100000 >
1#
#100000
0#
#101000
19
b100001 >
1#
#102000
0#
#103000
1*
b100010 >
1#
#104000
0#
#105000
b100011 >
1#
#106000
0#
#107000
b100100 >
1#
#108000
0#
#109000
09
b100101 >
1#
#110000
0#
#111000
0*
b100110 >
1#
#112000
0#
#113000
b100111 >
1#
#114000
0#
#115000
b0 >
1<
1#
#116000
b10000 D
1.
0#
#117000
1C
04
b10000 I
19
b1 >
0<
1#
#118000
b1 J
0.
0#
#119000
18
z*
b10 >
16
1#
1+
#120000
b10 J
0#
#121000
b11 >
b10000000000000 3
b10000000000000 ?
b10000000000000 B
b1 @
1#
#122000
b11 J
0#
#123000
b100 >
b10 @
1#
#124000
b100 J
0#
#125000
09
b101 >
b10100000000000 3
b10100000000000 ?
b10100000000000 B
08
b11 @
1#
0+
#126000
b101 J
0#
#127000
b10000000000000 3
b10000000000000 ?
b10000000000000 B
b110 >
b100 @
1#
#128000
b110 J
0#
#129000
b111 >
b101 @
1#
#130000
b111 J
0#
#131000
b1000 >
b110 @
1#
#132000
b1000 J
0#
#133000
19
b1001 >
18
b111 @
1#
1+
#134000
b1001 J
0#
#135000
b10000010000000 3
b10000010000000 ?
b10000010000000 B
b1010 >
b1000 @
1#
#136000
b1010 J
0#
#137000
b1011 >
b10000010100000 3
b10000010100000 ?
b10000010100000 B
b1001 @
1#
#138000
b1011 J
0#
#139000
b1100 >
b1010 @
1#
#140000
b1100 J
0#
#141000
09
b1101 >
b10000010101000 3
b10000010101000 ?
b10000010101000 B
08
b1011 @
1#
0+
#142000
b1101 J
0#
#143000
b10000010100000 3
b10000010100000 ?
b10000010100000 B
b1110 >
b1100 @
1#
#144000
b1110 J
0#
#145000
b1111 >
b1101 @
1#
#146000
b1111 J
0#
#147000
b100000 D
b10000 >
11
b1110 @
1#
#148000
b10000 J
0#
#149000
b1000000 D
b10000010100000 $
b10000010100000 /
b10000010100000 H
1!
b100000 I
19
b10001 >
b0 @
1#
#150000
b0 J
0#
#151000
02
06
07
05
b0 $
b0 /
b0 H
0!
b10010 >
b1000000 I
01
b1 @
1#
#152000
0#
#153000
z8
1#
#154000
0#
#155000
1#
#156000
0#
#157000
1#
#158000
0#
#159000
1#
#160000
0#
#161000
1#
#162000
0#
#163000
1#
#164000
0#
#165000
1#
#166000
0#
#167000
1#
#168000
0#
#169000
b1000000 D
1#
1-
