DAT/modules/DMA/Registers.v
module Registers(Block_Size_Register, Block_Count_Register, Transfer_Mode_Register, Present_State_Register, Block_Gap_Control_Register, Command_Register);

  output [15:0] Block_Size_Register;     //Offset 004h, interesa bit [11:0] 
  output [15:0] Block_Count_Register;    //Offset 006h, interesan todos los bits
  output [15:0] Transfer_Mode_Register;  //Offset 00Ch, interesan los bits 05, 04, 01,00.
  output [31:0] Present_State_Register;  //Offset 024h, interesan los bits 09,08.
  output [7:0]  Block_Gap_Control_Register;    //Offset 02Ah, interesan los bits 0,1.
  output [15:0]  Command_Register;        //Offset 00Eh, interesan los bits 6 y 7.
  

  reg [15:0] Block_Size_Register;    
  reg [15:0] Block_Count_Register;    
  reg [15:0] Transfer_Mode_Register; 
  reg [31:0] Present_State_Register; 
  reg [7:0]  Block_Gap_Control_Register;    
  reg [15:0]  Command_Register;  

initial begin
//Interesan
Block_Size_Register[11:0] <= 1; 
Block_Count_Register[15:0] <=1;
Transfer_Mode_Register[5]  <=1;
Transfer_Mode_Register[4]  <=1;
Transfer_Mode_Register[1]  <=1;
Transfer_Mode_Register[0]  <=1;
Present_State_Register[9]  <=1;
Present_State_Register[8]  <=1;
Block_Gap_Control_Register[0] <=1;
Block_Gap_Control_Register[1] <=1;
Command_Register[6]<=1;
Command_Register[7]<=1;

//No Interesan
Block_Size_Register[15:12] <= 0; 
Transfer_Mode_Register[2]  <= 0;
Transfer_Mode_Register[3]  <= 0;
Transfer_Mode_Register[15:6]<=0;
Present_State_Register[31:10]  <=0;
Present_State_Register[7:0]  <=0;
Block_Gap_Control_Register[7:2] <=0;
Command_Register[5:0] <=0;
Command_Register[15:8] <=0;
end    
endmodule

DAT/modules/DMA/Transferencia.v
module transferencia(Permiso_Transf, Data_Transfer_Direction_Select, DAT_LEN, DAT_ADR, transferencia_finalizada);

  parameter WAIT= 4'b0001; //DirecciónTransferencia
  parameter CARD_TO_HOST= 4'b0010;
  parameter HOST_TO_CARD= 4'b0100;

input Permiso_Transf;
input Data_Transfer_Direction_Select;
input [15:0] DAT_LEN;
input [63:0] DAT_ADR;

output transferencia_finalizada;

wire Permiso_Transf;
wire Data_Transfer_Direction_Select;
wire [15:0] DAT_LEN;
wire [63:0] DAT_ADR;

reg transferencia_finalizada=0;
reg [15:0] transfer_data_length=0;

always @(*) begin 
if (transfer_data_length==DAT_LEN) begin
transferencia_finalizada<=1;
end

else begin
transferencia_finalizada<=transferencia_finalizada;
end 
end

endmodule

DAT/modules/DMA/TransferType.v
module TipoDeTransferencia(Multi_Single_Block_Select, Block_Count_Enable,Transfer_Type);
input  Multi_Single_Block_Select;
input  Block_Count_Enable;


output [1:0] Transfer_Type;

wire Multi_Single_Block_Select;
wire Block_Count_Enable;


reg [1:0] Transfer_Type;
reg [1:0] Temporal; 

  parameter Single_Transfer  = 2'b00; 
  parameter Infinite_Transfer  = 2'b01;
  parameter Multiple_Transfer  = 2'b10;
  parameter Stop_Multiple_Transfer  = 2'b11;


always @(*)
begin
 Temporal[1]<=Multi_Single_Block_Select;
 Temporal[0]<=Block_Count_Enable;

case(Temporal)  
				2'b00:  begin 
					Transfer_Type<=Single_Transfer;
					
					end    

				2'b01:  begin 
					Transfer_Type<=Single_Transfer;
					end

				2'b10:  begin
					Transfer_Type<=Infinite_Transfer;
					end
					
					
				2'b11:	begin
 
					if (Block_Count_Enable==0) begin
					Transfer_Type<= Stop_Multiple_Transfer;
					end
					else begin
					Transfer_Type<= Multiple_Transfer;
					end


					end
				//default: 
         				//definir
      				endcase

end 
endmodule

DAT/modules/DMA/Descriptor_Table.v
module Descriptor_Table (SYS_ADR, Descriptor_Line);
input  [63:0] SYS_ADR;
output [95:0] Descriptor_Line;

wire   [63:0] SYS_ADR;
reg   [95:0]  Descriptor_Line; 

initial begin
Descriptor_Line[0]<=1;        //Valid
Descriptor_Line[1]<=0;        //End
Descriptor_Line[2]<=0;        //Int
Descriptor_Line[3]<=0;   
Descriptor_Line[4]<=0;        //Act1
Descriptor_Line[5]<=1;        //Act2
Descriptor_Line[15:6]<=0;     //Rsv
Descriptor_Line[31:16]<= 1;   //Length 
Descriptor_Line[95:32]<= 1;   //Address
end
endmodule

DAT/modules/DMA/TransicionEstados.v

module ADMA(clk, DMA_Interrupt, ADMA_Error, Transfer_complete, Initial_ADMA_System_Address, Block_Size_Register, Block_Count_Register, Transfer_Mode_Register, Present_State_Register, Block_Gap_Control_Register, Command_Register, ADMA_System_Address_Register, enb_DMA_Interrupt, ack_DMA_Interrupt,  enb_ADMA_Error, ack_ADMA_Error, enb_Transfer_complete, ack_Transfer_complete, enb_ADMA_System_Address_Register, ack_ADMA_System_Address_Register, Permiso_Transf);


  parameter ST_STOP  = 4'b0001; //Estados
  parameter ST_FDS  = 4'b0010;
  parameter ST_CADR  = 4'b0100;
  parameter ST_TFR  = 4'b1000;

  parameter WAIT= 4'b0001; //DirecciónTransferencia
  parameter CARD_TO_HOST= 4'b0010;
  parameter HOST_TO_CARD= 4'b0100;

  parameter Single_Transfer  = 2'b00; //Tipos de Transferencia
  parameter Infinite_Transfer  = 2'b01;
  parameter Multiple_Transfer  = 2'b10;
  parameter Stop_Multiple_Transfer  = 2'b11;


  input ack_DMA_Interrupt;
  input ack_ADMA_Error;
  input ack_Transfer_complete;
  input ack_ADMA_System_Address_Register;
  input clk;
  input [63:0] Initial_ADMA_System_Address;
  input [15:0] Block_Size_Register;     //Offset 004h, interesa bit [11:0] 
  input [15:0] Block_Count_Register;    //Offset 006h, interesan todos los bits
  input [15:0] Transfer_Mode_Register;  //Offset 00Ch, interesan los bits 05, 04, 01,00.
  input [31:0] Present_State_Register;  //Offset 024h, interesan los bits 09,08.
  input [7:0]  Block_Gap_Control_Register;    //Offset 02Ah, interesan los bits 0,1.
  input [15:0]  Command_Register;        //Offset 00Eh, interesan los bits 6 y 7. 

  output enb_DMA_Interrupt;
  output enb_ADMA_Error;
  output enb_Transfer_complete;
  output enb_ADMA_System_Address_Register;
  output DMA_Interrupt;     //Normal_Interrupt_Status_Register   Offset  030h  bit 3. 
  output ADMA_Error;        //Error Interrupt Status Register    Offset 032h bit 9.
  output Transfer_complete; //Normal_Interrupt_Status_Register   Offset  030h  bit 1.
  output [63:0] ADMA_System_Address_Register; // (Offset 058h) 
  output Permiso_Transf;
  
  wire ack_DMA_Interrupt;
  wire ack_ADMA_Error;
  wire ack_Transfer_complete;
  wire ack_ADMA_System_Address_Register;
  wire clk;
  wire  [63:0] Initial_ADMA_System_Address;      
  wire  [15:0] Block_Size_Register; 
  wire  [15:0] Block_Count_Register; 
  wire  [15:0] Transfer_Mode_Register;
  wire  [31:0] Present_State_Register;
  wire  [7:0] Block_Gap_Control_Register;
  wire  [15:0]  Command_Register;

  wire [95:0] Descriptor_Line;
  wire [1:0] Transfer_Type; 
  
  wire transferencia_finalizada;  

  reg enb_DMA_Interrupt=0;
  reg enb_ADMA_Error=0;
  reg enb_Transfer_complete=0;
  reg enb_ADMA_System_Address_Register=0;
  reg DMA_Interrupt=0; 
  reg ADMA_Error=0; 
  reg Transfer_complete=0;
  reg Command_Reg_Write_or_Continue;    //REVISAR, CUANDO SE DA UNA ESCRITURA EN EL command register?
  reg [63:0] ADMA_System_Address_Register; // (Offset 058h) 
  reg [3:0] Present_State=ST_STOP; 
  reg [3:0] Next_State=ST_STOP; 
  reg [63:0] SYS_ADR=0;             //Registros Internos
  reg [15:0] DAT_LEN=0;
  reg [63:0] DAT_ADR=0;
  reg Valid=1;
  reg End=0;
  reg Int=0;
  reg Act1=0;
  reg Act2=0; 
  reg [1:0] Act=0;                    //Act corresponde a la unión  de Act1+Act2 (Por simplicidad)
  reg TFC=0;
  reg Tran=0;
  reg [11:0] Transfer_Block_Size; 
  reg Multi_Single_Block_Select;
  reg Data_Transfer_Direction_Select;
  reg Block_Count_Enable; 
  reg DMA_Eneable; 
  reg Read_Transfer_Active;
  reg Write_Transfer_Active; 
  reg Stop_At_Block_Gap_Request;
  reg Continue_Request;
  reg [1:0] Command_Type; 
  reg [3:0] Transfer_Mode_Direction;
  reg Permiso_Transf=0;
  

Descriptor_Table  table1   (SYS_ADR, Descriptor_Line);

TipoDeTransferencia t1 (Multi_Single_Block_Select, Block_Count_Enable,Transfer_Type);

transferencia tran1 (Permiso_Transf, Data_Transfer_Direction_Select, DAT_LEN, DAT_ADR, transferencia_finalizada);


///////////////////////////////////////////////////////////////////////////////////////
always @(*) begin 

Transfer_Block_Size <= Block_Size_Register[11:0];
Multi_Single_Block_Select<=Transfer_Mode_Register[5];        
Data_Transfer_Direction_Select<=Transfer_Mode_Register[4];        
Block_Count_Enable<=Transfer_Mode_Register[1];        
DMA_Eneable<=Transfer_Mode_Register[0];  
Read_Transfer_Active<=Present_State_Register[9];
Write_Transfer_Active<= Present_State_Register[8];
Stop_At_Block_Gap_Request<= Block_Gap_Control_Register[0];
Continue_Request<= Block_Gap_Control_Register[1];
Command_Type[0] <= Command_Register[6];
Command_Type[1] <= Command_Register[7];
ADMA_System_Address_Register<=SYS_ADR;

Command_Reg_Write_or_Continue<=1;




///////////////////////////////////////////////////////////////////////////////////////  
if (Present_State==ST_FDS) begin  
//Atributos a partir del Descriptor_Line
Valid <= Descriptor_Line[0];   
End <= Descriptor_Line[1];
Int <= Descriptor_Line[2];
Act1 <= Descriptor_Line[4];
Act2 <= Descriptor_Line[5];
Act[0] <=Act1;               //Obtengo Act
Act[1] <=Act2;
DAT_LEN <= Descriptor_Line[31:16];  //Length y Address
DAT_ADR <= Descriptor_Line[95:32];
end 

else begin
Valid <= Valid;   
End <= End;
Int <= Int;
Act1 <= Act1;
Act2 <= Act2;
Act[0] <= Act[0];               
Act[1] <=Act[1];
DAT_LEN <= DAT_LEN;  
DAT_ADR <= DAT_ADR;
end

///////////////////////////////////

		case(Data_Transfer_Direction_Select)
		     0: begin 
			Transfer_Mode_Direction<=HOST_TO_CARD;
			end

		     1: begin
			Transfer_Mode_Direction<=CARD_TO_HOST;
			end 

		     default: begin
		        Transfer_Mode_Direction<=WAIT; 
			      end 

		endcase  
end


///////////////////////////////////////////////////////////////////////////////////////
always @(posedge clk) begin  

case(Present_State)
	ST_STOP: begin 
			if(Command_Reg_Write_or_Continue==1) 
					begin
                          			Next_State <= ST_FDS;			    
				        end
			else	
					begin
                          			Next_State <= ST_STOP;
					end
		  end                   

        
        ST_FDS:  begin
		 TFC<=0;
			     if(Valid==1) 
					     begin
					     Next_State <= ST_CADR;
				             end
			      else	
					     begin
					     Next_State <= ST_FDS;
					    end
		  end


       ST_CADR: begin
			
			if (Tran==1) begin
					Next_State <= ST_TFR;
				     end 
			else  begin

					if (End==0) begin
						Next_State <= ST_FDS;
						end 
					else begin
						Next_State <= ST_STOP;
						end

				end 
		end
     ST_TFR:

	        begin 
	             if(TFC==1 & (End==1 | Stop_At_Block_Gap_Request==1))
		           Next_State <= ST_STOP;
	             else 
		           Next_State <= ST_TFR;	

                 end
        

         default:   
	 		Next_State <= ST_STOP;
         
      endcase
end
///////////////////////////////////////////////////////////////////////////////////////////////////////

always @(*) begin  
case(Present_State)


	ST_STOP: begin 
			SYS_ADR<=Initial_ADMA_System_Address;
			ADMA_System_Address_Register<=SYS_ADR;
			enb_ADMA_System_Address_Register<=1;
					
			if(ack_ADMA_System_Address_Register==1)begin

                          Present_State <= Next_State;
			  enb_ADMA_System_Address_Register<=0;
			 end 

			else begin
			  Present_State <= Present_State;
			     end
		  end                   

        
        ST_FDS:  begin

		if(Next_State==ST_FDS)begin
				        ADMA_Error <=1;          
					DMA_Interrupt <=1; 
					enb_DMA_Interrupt<=1;
  					enb_ADMA_Error<=1;
					if(ack_DMA_Interrupt==1 & ack_ADMA_Error==1) begin
						Present_State <= Next_State;
						enb_DMA_Interrupt<=0;
  						enb_ADMA_Error<=0;
					   end 
					else begin
						Present_State <= Present_State;
					  end
		end 

		else begin
		Present_State <= Next_State;
		end

		end


        ST_CADR: begin
				ADMA_Error <=0;          
				DMA_Interrupt <=0; 
				ADMA_System_Address_Register<=SYS_ADR;
				enb_ADMA_System_Address_Register<=1;
				if(ack_ADMA_System_Address_Register==1)begin
					Present_State <= Next_State;
					enb_ADMA_System_Address_Register<=0;
				end
				
				else begin
			 		 Present_State <= Present_State;
			        end
		end
        ST_TFR:
	        begin 
			Present_State <= Next_State;	
                 end

        default: 
	 		Present_State <= Present_State;
      endcase
end
////////////////////////////////////////////////////////////////////////////////////


always @(posedge clk) begin 
if(Present_State==ST_CADR)  begin
		case(Act)  
				2'b00:  begin   //NOP
					SYS_ADR <= SYS_ADR+ 8;   
					Tran=0;
					end    

				2'b01:  begin  //RSV
					SYS_ADR <= SYS_ADR+ 8;   
					Tran=0;
					end

				2'b10:  begin  //TRAN
					SYS_ADR <= SYS_ADR+ 8;
					Tran=1;
					end

				2'b11:	begin  //LINK
					SYS_ADR <= DAT_ADR;    
					Tran=0;
					end
				default: begin
					SYS_ADR <= SYS_ADR;   
					Tran<=Tran;
					 end
         		                  
      				endcase
end

 else begin
 SYS_ADR <= SYS_ADR;   
 Tran<=Tran;
 end
end
////////////////////////////////////////////////////////////////////////////////////////////////////
always @(*) begin 
	if(Present_State==ST_TFR)  begin
		Permiso_Transf<=1;

		if(transferencia_finalizada==1)begin
		TFC<=1;
		Permiso_Transf<=0;
		end
		else begin
		Permiso_Transf<=Permiso_Transf;
		end
	end 
	else begin
		Permiso_Transf<=0;
	end
end
///////////////////////////////////////////////////////////////////////////////////////////////////
endmodule

DAT/modules/DMA/Probador.v
`timescale 1 ns / 1 ps
module probador(clk, Initial_ADMA_System_Address, ack_DMA_Interrupt, ack_ADMA_Error, ack_Transfer_complete, ack_ADMA_System_Address_Register);


output  clk; 
output  [63:0] Initial_ADMA_System_Address;
output  ack_DMA_Interrupt;
output  ack_ADMA_Error;
output ack_Transfer_complete;
output ack_ADMA_System_Address_Register;

reg        clk;
reg  [63:0] Initial_ADMA_System_Address;
reg  ack_DMA_Interrupt;
reg  ack_ADMA_Error;
reg ack_Transfer_complete;
reg ack_ADMA_System_Address_Register;

initial begin
   ack_DMA_Interrupt=1;
   ack_ADMA_Error=1;
   ack_Transfer_complete=1;
   ack_ADMA_System_Address_Register=1;
   clk=0;
   Initial_ADMA_System_Address=1; 
   #1000 $finish;
   

   end

   always #100 clk <= !clk;
  
   
  
endmodule

DAT/modules/DMA/aFIFO.v
module asynchronous_fifo
        //Reading port
	(output reg  [DATA_WIDTH-1:0]       Data_out, 
	output reg                          Empty_out, //almost empty signal
	input wire                          ReadEn_in,
	input wire                          RClk,        
	//Writing port.	 
	input wire  [DATA_WIDTH-1:0]        Data_in,  
	output reg                          Full_out, //almost full signal
	input wire                          WriteEn_in,
	input wire                          WClk,
	output reg			    ack_write); // FIXME falta definir esta bandera 
	parameter    DATA_WIDTH    = 32;
        parameter    FIFO_length = 1024;

	//states	
	parameter reset = 0;
	parameter idle = 4'b0001;
	parameter info_onFIFO = 4'b0010;
	parameter write_state = 4'b0100;
	parameter read_state = 4'b1000;

	reg [3:0]state = 0;
	wire [39:0] cuarenta_bits;
	reg [FIFO_length -1: 0] buffer;
	assign cuarenta_bits = buffer[39:0];
	reg [10:0] count = 0;

	always@ (posedge WClk) begin
		case (state) 
			default:
				begin
					state <= idle;
					Data_out <= 0;
					count <= 0;
					buffer <= 0;
				end	
				
			reset:
				begin
					state <= idle;
					Data_out <= 0;
					count <= 0;
					buffer <= 0;
				end	
			idle:	
				begin
					if (WriteEn_in) begin
						state <= write_state;
					end else begin
						state <= idle;
					end
				end
			write_state:
				begin 
					count <= count + DATA_WIDTH;
					buffer <= {buffer[FIFO_length - DATA_WIDTH - 1: 0], Data_in};
					if(!WriteEn_in || Full_out) begin
						state <= idle;					
					end else begin
						state <= write_state;
 		
					end
				end	
		endcase
	end

	always@ (posedge RClk) begin
		if(ReadEn_in && !Empty_out) begin
			Data_out <= buffer[count - 1 -: DATA_WIDTH];
		end
	end

	always@ (negedge RClk) begin
		if(ReadEn_in && !Empty_out) begin	
			count <= count - DATA_WIDTH;	
		end
	end

	always@(*) begin
		//Full signal generation
		if(count == FIFO_length - DATA_WIDTH) begin
			Full_out = 1;		
		end else begin
			Full_out = 0;
		end
		
		//Empty signal generation
		if((count == DATA_WIDTH) || (count == 0)) begin
			Empty_out = 1;		
		end else begin
			Empty_out = 0;
		end
		
	end

endmodule

DAT/modules/DMA/fifo_testbench.v
module fifo_testbench; //testbench y probador de fifo

wire clk;
wire DMA_Interrupt;
wire ADMA_Error;
wire Transfer_complete;
wire [63:0] Initial_ADMA_System_Address;


wire  [15:0] Block_Size_Register; 
wire  [15:0] Block_Count_Register; 
wire  [15:0] Transfer_Mode_Register;
wire  [31:0] Present_State_Register;
wire  [7:0] Block_Gap_Control_Register;
wire  [15:0]  Command_Register;
wire [63:0] ADMA_System_Address_Register;

wire enb_DMA_Interrupt;
wire ack_DMA_Interrupt;
wire enb_ADMA_Error;
wire ack_ADMA_Error;
wire enb_Transfer_complete;
wire ack_Transfer_complete;
wire enb_ADMA_System_Address_Register;
wire ack_ADMA_System_Address_Register;
wire Permiso_Transf;

	reg [n-1 : 0] parallel;
	reg sd_clock; 
	reg clock;
	reg enable_write;
	reg enable_read;
	reg Clear_in;	           
	parameter n = 32;
	wire [n-1: 0] Data_out;


	reg [n2-1 : 0] parallel2;
	reg sd_clock2;
	reg clock2;
	reg enable_write2;
	reg enable_read2;
	reg Clear_in2;	           
	parameter n2 = 32;
	wire [n2-1: 0] Data_out2;
	
//Lectura
	asynchronous_fifo FIFO
        //Reading port
	(Data_out, 
	Empty_out, //almost empty signal
	enable_read,
	sd_clock,        
	//Writing port.	 
	parallel,  
	Full_out, //almost full signal
	enable_write,
	clock,	 
	ack_write);
	
//Escritura
	asynchronous_fifo FIFO2
        //Reading port
	(Data_out2, 
	Empty_out2, //almost empty signal
	enable_read2,
	sd_clock2,        
	//Writing port.	 
	parallel2,  
	Full_out2, //almost full signal
	enable_write2,
	clock2,	 
	ack_write2);

	initial begin


		Clear_in = 1;
		enable_write = 1;
		enable_read = 1;
		sd_clock = 0;
		clock = 0;
	#4	parallel = 32'hFCB01AA;
	#5	parallel = 32'hFCBCAFE;
	#4	parallel = 32'h11CAFEF;
	#4	parallel = 32'h1111000;
	#6	parallel = 32'hFFFFFFF;
	#3	parallel = 32'h11CAFEF;
	#4	parallel = 4'b1011;
	#5	parallel = 4'b0000;
	#3	parallel = 4'b1110;
	#5	parallel = 4'b0111;
	#6	parallel = 4'b0101;
	#5	parallel = 4'b0000;
	#5	enable_read = 0;
	#30	enable_read = 1;



		Clear_in2 = 1;
		enable_write2 = 1;
		enable_read2 = 1;
		sd_clock2 = 0;
		clock2 = 0;
	#4	parallel2 = 32'hFCB01AA;
	#5	parallel2 = 32'hFCBCAFE;
	#4	parallel2 = 32'h11CAFEF;
	#4	parallel2 = 32'h1111000;
	#6	parallel2 = 32'hFFFFFFF;
	#3	parallel2 = 32'h11CAFEF;
	#4	parallel2 = 4'b1011;
	#5	parallel2 = 4'b0000;
	#3	parallel2 = 4'b1110;
	#5	parallel2 = 4'b0111;
	#6	parallel2 = 4'b0101;
	#5	parallel2 = 4'b0000;
	#5	enable_read2 = 0;
	#30	enable_read2 = 1;

   #200 $finish;
   end

probador p1 (clk, Initial_ADMA_System_Address, ack_DMA_Interrupt, ack_ADMA_Error, ack_Transfer_complete, ack_ADMA_System_Address_Register);

   ADMA   adma1 (clk, DMA_Interrupt, ADMA_Error, Transfer_complete, Initial_ADMA_System_Address, Block_Size_Register, Block_Count_Register, Transfer_Mode_Register, Present_State_Register, Block_Gap_Control_Register, Command_Register, ADMA_System_Address_Register, enb_DMA_Interrupt, ack_DMA_Interrupt,  enb_ADMA_Error, ack_ADMA_Error, enb_Transfer_complete, ack_Transfer_complete, enb_ADMA_System_Address_Register, ack_ADMA_System_Address_Register, Permiso_Transf);

   Registers  r1  (Block_Size_Register,Block_Count_Register,Transfer_Mode_Register,Present_State_Register,Block_Gap_Control_Register, Command_Register);

  initial begin       
     $dumpfile("testbench.vcd");          
     $dumpvars(0,fifo_testbench);
  end

   always #6 sd_clock = !sd_clock;
   always #2 clock = !clock;
endmodule // probador

DAT/modules/DMA/testbench.vcd
$date
	Fri Dec  9 06:18:49 2016
$end
$version
	Icarus Verilog
$end
$timescale
	1ps
$end
$scope module fifo_testbench $end
$var wire 1 ! enb_Transfer_complete $end
$var wire 1 " enb_DMA_Interrupt $end
$var wire 1 # enb_ADMA_System_Address_Register $end
$var wire 1 $ enb_ADMA_Error $end
$var wire 1 % clk $end
$var wire 1 & ack_write2 $end
$var wire 1 ' ack_write $end
$var wire 1 ( ack_Transfer_complete $end
$var wire 1 ) ack_DMA_Interrupt $end
$var wire 1 * ack_ADMA_System_Address_Register $end
$var wire 1 + ack_ADMA_Error $end
$var wire 1 , Transfer_complete $end
$var wire 16 - Transfer_Mode_Register [15:0] $end
$var wire 32 . Present_State_Register [31:0] $end
$var wire 1 / Permiso_Transf $end
$var wire 64 0 Initial_ADMA_System_Address [63:0] $end
$var wire 1 1 Full_out2 $end
$var wire 1 2 Full_out $end
$var wire 1 3 Empty_out2 $end
$var wire 1 4 Empty_out $end
$var wire 32 5 Data_out2 [31:0] $end
$var wire 32 6 Data_out [31:0] $end
$var wire 1 7 DMA_Interrupt $end
$var wire 16 8 Command_Register [15:0] $end
$var wire 16 9 Block_Size_Register [15:0] $end
$var wire 8 : Block_Gap_Control_Register [7:0] $end
$var wire 16 ; Block_Count_Register [15:0] $end
$var wire 64 < ADMA_System_Address_Register [63:0] $end
$var wire 1 = ADMA_Error $end
$var reg 1 > Clear_in $end
$var reg 1 ? Clear_in2 $end
$var reg 1 @ clock $end
$var reg 1 A clock2 $end
$var reg 1 B enable_read $end
$var reg 1 C enable_read2 $end
$var reg 1 D enable_write $end
$var reg 1 E enable_write2 $end
$var reg 32 F parallel [31:0] $end
$var reg 32 G parallel2 [31:0] $end
$var reg 1 H sd_clock $end
$var reg 1 I sd_clock2 $end
$scope module FIFO $end
$var wire 32 J Data_in [31:0] $end
$var wire 1 H RClk $end
$var wire 1 B ReadEn_in $end
$var wire 1 @ WClk $end
$var wire 1 D WriteEn_in $end
$var wire 40 K cuarenta_bits [39:0] $end
$var reg 32 L Data_out [31:0] $end
$var reg 1 4 Empty_out $end
$var reg 1 2 Full_out $end
$var reg 1 ' ack_write $end
$var reg 1024 M buffer [1023:0] $end
$var reg 11 N count [10:0] $end
$var reg 4 O state [3:0] $end
$upscope $end
$scope module FIFO2 $end
$var wire 32 P Data_in [31:0] $end
$var wire 1 I RClk $end
$var wire 1 C ReadEn_in $end
$var wire 1 A WClk $end
$var wire 1 E WriteEn_in $end
$var wire 40 Q cuarenta_bits [39:0] $end
$var reg 32 R Data_out [31:0] $end
$var reg 1 3 Empty_out $end
$var reg 1 1 Full_out $end
$var reg 1 & ack_write $end
$var reg 1024 S buffer [1023:0] $end
$var reg 11 T count [10:0] $end
$var reg 4 U state [3:0] $end
$upscope $end
$scope module adma1 $end
$var wire 1 V transferencia_finalizada $end
$var wire 1 % clk $end
$var wire 1 ( ack_Transfer_complete $end
$var wire 1 ) ack_DMA_Interrupt $end
$var wire 1 * ack_ADMA_System_Address_Register $end
$var wire 1 + ack_ADMA_Error $end
$var wire 2 W Transfer_Type [1:0] $end
$var wire 16 X Transfer_Mode_Register [15:0] $end
$var wire 32 Y Present_State_Register [31:0] $end
$var wire 64 Z Initial_ADMA_System_Address [63:0] $end
$var wire 96 [ Descriptor_Line [95:0] $end
$var wire 16 \ Command_Register [15:0] $end
$var wire 16 ] Block_Size_Register [15:0] $end
$var wire 8 ^ Block_Gap_Control_Register [7:0] $end
$var wire 16 _ Block_Count_Register [15:0] $end
$var reg 1 = ADMA_Error $end
$var reg 64 ` ADMA_System_Address_Register [63:0] $end
$var reg 2 a Act [1:0] $end
$var reg 1 b Act1 $end
$var reg 1 c Act2 $end
$var reg 1 d Block_Count_Enable $end
$var reg 1 e Command_Reg_Write_or_Continue $end
$var reg 2 f Command_Type [1:0] $end
$var reg 1 g Continue_Request $end
$var reg 64 h DAT_ADR [63:0] $end
$var reg 16 i DAT_LEN [15:0] $end
$var reg 1 j DMA_Eneable $end
$var reg 1 7 DMA_Interrupt $end
$var reg 1 k Data_Transfer_Direction_Select $end
$var reg 1 l End $end
$var reg 1 m Int $end
$var reg 1 n Multi_Single_Block_Select $end
$var reg 4 o Next_State [3:0] $end
$var reg 1 / Permiso_Transf $end
$var reg 4 p Present_State [3:0] $end
$var reg 1 q Read_Transfer_Active $end
$var reg 64 r SYS_ADR [63:0] $end
$var reg 1 s Stop_At_Block_Gap_Request $end
$var reg 1 t TFC $end
$var reg 1 u Tran $end
$var reg 12 v Transfer_Block_Size [11:0] $end
$var reg 4 w Transfer_Mode_Direction [3:0] $end
$var reg 1 , Transfer_complete $end
$var reg 1 x Valid $end
$var reg 1 y Write_Transfer_Active $end
$var reg 1 $ enb_ADMA_Error $end
$var reg 1 # enb_ADMA_System_Address_Register $end
$var reg 1 " enb_DMA_Interrupt $end
$var reg 1 ! enb_Transfer_complete $end
$scope module t1 $end
$var wire 1 d Block_Count_Enable $end
$var wire 1 n Multi_Single_Block_Select $end
$var reg 2 z Temporal [1:0] $end
$var reg 2 { Transfer_Type [1:0] $end
$upscope $end
$scope module table1 $end
$var wire 64 | SYS_ADR [63:0] $end
$var reg 96 } Descriptor_Line [95:0] $end
$upscope $end
$scope module tran1 $end
$var wire 64 ~ DAT_ADR [63:0] $end
$var wire 16 !" DAT_LEN [15:0] $end
$var wire 1 k Data_Transfer_Direction_Select $end
$var wire 1 / Permiso_Transf $end
$var reg 16 "" transfer_data_length [15:0] $end
$var reg 1 V transferencia_finalizada $end
$upscope $end
$upscope $end
$scope module p1 $end
$var reg 64 #" Initial_ADMA_System_Address [63:0] $end
$var reg 1 + ack_ADMA_Error $end
$var reg 1 * ack_ADMA_System_Address_Register $end
$var reg 1 ) ack_DMA_Interrupt $end
$var reg 1 ( ack_Transfer_complete $end
$var reg 1 % clk $end
$upscope $end
$scope module r1 $end
$var reg 16 $" Block_Count_Register [15:0] $end
$var reg 8 %" Block_Gap_Control_Register [7:0] $end
$var reg 16 &" Block_Size_Register [15:0] $end
$var reg 16 '" Command_Register [15:0] $end
$var reg 32 (" Present_State_Register [31:0] $end
$var reg 16 )" Transfer_Mode_Register [15:0] $end
$upscope $end
$upscope $end
$enddefinitions $end
#0
$dumpvars
b110011 )"
b1100000000 ("
b11000000 '"
b1 &"
b11 %"
b1 $"
b1 #"
b0 ""
b0 !"
b0 ~
b100000000000000010000000000100001 }
b1 |
b10 {
b11 z
1y
1x
b10 w
b1 v
0u
0t
1s
b1 r
1q
b1 p
b1 o
1n
0m
0l
1k
1j
b0 i
b0 h
1g
b11 f
1e
1d
0c
0b
b0 a
b1 `
b1 _
b11 ^
b1 ]
b11000000 \
b100000000000000010000000000100001 [
b1 Z
b1100000000 Y
b110011 X
b10 W
1V
b0 U
b0 T
bx S
bx R
bx Q
bx P
b0 O
b0 N
bx M
bx L
bx K
bx J
xI
0H
bx G
bx F
xE
1D
xC
1B
xA
0@
x?
1>
0=
b1 <
b1 ;
b11 :
b1 9
b11000000 8
07
bx 6
bx 5
14
13
02
01
b1 0
0/
b1100000000 .
b110011 -
0,
1+
1*
1)
1(
x'
x&
0%
0$
0#
0"
0!
$end
#2000
b0 K
b0 M
b0 6
b0 L
b1 O
1@
#4000
0@
b1111110010110000000110101010 F
b1111110010110000000110101010 J
#6000
b100 O
1@
1H
#8000
0@
#9000
b1111110010111100101011111110 F
b1111110010111100101011111110 J
#10000
b1111110010111100101011111110 K
b1111110010111100101011111110 M
b100000 N
1@
#12000
0@
0H
#13000
b1000111001010111111101111 F
b1000111001010111111101111 J
#14000
b1111111000000001000111001010111111101111 K
04
b111111001011110010101111111000000001000111001010111111101111 M
b1000000 N
1@
#16000
0@
#17000
b1000100010001000000000000 F
b1000100010001000000000000 J
#18000
b1110111100000001000100010001000000000000 K
b11111100101111001010111111100000000100011100101011111110111100000001000100010001000000000000 M
b1100000 N
b1111110010111100101011111110 6
b1111110010111100101011111110 L
1@
1H
#20000
0@
#22000
b1000100010001000000000000 K
b1111110010111100101011111110000000010001110010101111111011110000000100010001000100000000000000000001000100010001000000000000 M
b10000000 N
1@
#23000
b1111111111111111111111111111 F
b1111111111111111111111111111 J
#24000
b1100000 N
0@
0H
#26000
b1000111001010111111101111 K
b111111001011110010101111111000000001000111001010111111101111000000010001000100010000000000000000000100010001000100000000000000000001000111001010111111101111 M
b10000000 N
1@
b1000111001010111111101111 F
b1000111001010111111101111 J
#28000
0@
#30000
b1110111100000000000000000000000000001011 K
b11111100101111001010111111100000000100011100101011111110111100000001000100010001000000000000000000010001000100010000000000000000000100011100101011111110111100000000000000000000000000001011 M
b10100000 N
b1000111001010111111101111 6
b1000111001010111111101111 L
1@
b1011 F
b1011 J
1H
#32000
0@
#34000
b101100000000000000000000000000001011 K
b1111110010111100101011111110000000010001110010101111111011110000000100010001000100000000000000000001000100010001000000000000000000010001110010101111111011110000000000000000000000000000101100000000000000000000000000001011 M
b11000000 N
1@
#35000
b0 F
b0 J
#36000
b10100000 N
0@
0H
#38000
b101100000000000000000000000000001110 K
b111111001011110010101111111000000001000111001010111111101111000000010001000100010000000000000000000100010001000100000000000000000001000111001010111111101111000000000000000000000000000010110000000000000000000000000000101100000000000000000000000000001110 M
b11000000 N
1@
b1110 F
b1110 J
#40000
0@
