CMD/capa_fisica/pad.v
module pad(output_input, enable, data_in, data_out, sd_clock, i_port, o_port);

   
	input output_input;	// salida (1) o entrada (0) (CCF)
	input enable;		// Habilitacion	(CCF)
	input data_in;		// Datos por enviar (wrapper P-S)
	input sd_clock;		// Reloj de la tarjeta SD
	input i_port;		// Linea de la tarjeta SD (SD)

	output data_out;	// Datos recibidos (wrapper S-P)
	output o_port;		// Linea hacia la tarjeta SD (SD)


	wire output_input;
	wire enable;
	wire data_in;
	wire sd_clock;
	wire i_port;

	reg data_out;
	reg o_port;

   
	always @(posedge sd_clock) begin
		if (enable) begin
			if (output_input == 1) begin
				o_port <= data_in;
				data_out <= 1'bz;
			end else begin
				o_port <= 1'bz;
				data_out <= i_port;
			end
		end else begin
			o_port <= 1'bz;
			data_out <= 1'bz;
		end
	end					

endmodule

CMD/PAD/probador.v
`timescale 1 ns / 1 ps

module probador (output_input, enable, data_in, sd_clock, i_port);

   output output_input;
   output enable;
   output data_in;
   output sd_clock;
   output i_port;

   reg output_input;
   reg enable;
   reg data_in;
   reg sd_clock;
   reg i_port;
            

   initial begin
	enable = 1;
	sd_clock = 0;

	output_input = 1;	
        data_in = 1;
      	#6 data_in = 0;
	#6 data_in = 1;

	#6 output_input = 0;
	i_port = 0;
	#6 i_port = 1;
	#6 i_port = 0;

	#5 $finish;
   end

   always #1 sd_clock = !sd_clock;

endmodule // probador

CMD/PAD/testbench.v
module testbench;                                // Se define un modulo de prueba

   wire output_input;
   wire enable;
   wire data_in;
   wire data_out;
   wire sd_clock;
   wire i_port;
   wire o_port;


  initial begin   
     $dumpfile("testbench.vcd");   
     $dumpvars(0,testbench);
  end
       

  probador valores (output_input, enable, data_in, sd_clock, i_port);

  pad c1 (output_input, enable, data_in, data_out, sd_clock, i_port, o_port);
   

endmodule // test

CMD/PAD/testbench.vcd
$date
	Mon Nov 28 19:23:35 2016
$end
$version
	Icarus Verilog
$end
$timescale
	1ps
$end
$scope module testbench $end
$var wire 1 ! sd_clock $end
$var wire 1 " output_input $end
$var wire 1 # o_port $end
$var wire 1 $ i_port $end
$var wire 1 % enable $end
$var wire 1 & data_out $end
$var wire 1 ' data_in $end
$scope module c1 $end
$var wire 1 ! sd_clock $end
$var wire 1 " output_input $end
$var wire 1 $ i_port $end
$var wire 1 % enable $end
$var wire 1 ' data_in $end
$var reg 1 & data_out $end
$var reg 1 # o_port $end
$upscope $end
$scope module valores $end
$var reg 1 ' data_in $end
$var reg 1 % enable $end
$var reg 1 $ i_port $end
$var reg 1 " output_input $end
$var reg 1 ! sd_clock $end
$upscope $end
$upscope $end
$enddefinitions $end
#0
$dumpvars
1'
x&
1%
x$
x#
1"
0!
$end
#1000
z&
1#
1!
#2000
0!
#3000
1!
#4000
0!
#5000
1!
#6000
0!
0'
#7000
0#
1!
#8000
0!
#9000
1!
#10000
0!
#11000
1!
#12000
0!
1'
#13000
1#
1!
#14000
0!
#15000
1!
#16000
0!
#17000
1!
#18000
0!
0$
0"
#19000
0&
z#
1!
#20000
0!
#21000
1!
#22000
0!
#23000
1!
#24000
0!
1$
#25000
1&
1!
#26000
0!
#27000
1!
#28000
0!
#29000
1!
#30000
0!
0$
#31000
0&
1!
