CMD/CMD/control_cmd.v
module control_cmd(new_command, clock, reset, cmd_argument, cmd_index, timeout_enable, serial_ready, ack_in, strobe_in, cmd_in, time_out, response, command_complete, command_index_error, strobe_out, ack_out, idle_out, cmd_out);

   
   input           new_command;           //Nuevo procreso del CMD   (WB---Reg)
   input           clock;                 //Reloj del dispositivo 
   input           reset;                 //Reinicio
   input [31 : 0]  cmd_argument;          //Argumento del comando  (Reg)
   input [5 : 0]   cmd_index;             //Indice del comando (Reg)
   input 	   timeout_enable;        //Habilitacion del timeout (Reg)
   input 	   serial_ready;          //Capa fisica lista (CF)
   input 	   ack_in;                 //Sincronizacion (CF)
   input           strobe_in;             //Fin del uso de la capa fisica (CF) 
   input [135 : 0] cmd_in;                //Respuesta recibida (CF)
   input 	   time_out;              //Ocurrencia de un timeout (CF)
   
   output [127 : 0] response;            //Respuesta escrita a los registros (Reg)
   output 	    command_complete;    //Fin del proceso de CMD  (Reg - WB)
   output 	    command_index_error; //Error de indice comandos (Reg)
   output 	    strobe_out;          //Solicitar el uso a la capa fisica (CF)
   output 	    ack_out;             //Sincronizacion (CF)
   output 	    idle_out;            //Enviar la capa fisica al estado idle (CF)
   output [39 : 0]  cmd_out;             //Parte de la trama por enviar (CF)

   wire           new_command;         
   wire           clock;              
   wire           reset;                
   wire [31 : 0]  cmd_argument;       
   wire [5 : 0]   cmd_index;         
   wire 	  timeout_enable;      
   wire 	  serial_ready;       
   wire 	  ack_in;           
   wire           strobe_in;         
   wire [135 : 0] cmd_in;               
   wire 	  time_out;              
   
   reg [127 : 0] response;            
   reg 	         command_complete;    
   reg 	         command_index_error; 
   reg 	         strobe_out;         
   reg 	         ack_out;            
   reg 	         idle_out;            
   reg [39 : 0]  cmd_out; 

   reg [3:0] state = 4'b0001;       
   reg [3:0] next_state;      
   

   //Declaracion de estados
     parameter reset_state = 4'b0001;
     parameter idle = 4'b0010;
     parameter setting_outputs = 4'b0100;
     parameter processing = 4'b1000;

   always @(posedge clock) begin
   	state <= next_state;
   end   


   always @(*) begin

      case (state)

	reset_state :
	  begin
	     response [127 : 0]  <= 128'h00000000000000000000000000000000;
	     command_complete    <= 0;
	     command_index_error <= 0;
	     strobe_out          <= 0;
	     ack_out             <= 0;
	     idle_out            <= 0;
	     cmd_out [39 : 0]     <= 0;

	     next_state <= idle;
	     
	  end

	idle :
	  begin
	     if (new_command == 1) begin
		next_state <= setting_outputs;
	     end else begin
		next_state <= idle;
	     end

	     idle_out <= 1;
	     
	  end

	setting_outputs :
	  begin
	     strobe_out <= 1;
	     
	     cmd_out[39] <= 0;
	     cmd_out[38] <= 1;
	     cmd_out[37:32] <= cmd_index[5:0];
	     cmd_out[31:0] <= cmd_argument[31:0];

	     next_state <= processing;
	     
	  end

	processing :
	  begin
	     if (strobe_in == 1) begin
		command_complete <= 1;
		ack_out <= 1;

		
	        response[127:0] <= cmd_in[127:0];               //***revisar lo del command_index_error***
								//*** del estado processing pasar al idle***
	        if (ack_in == 1) begin
		   next_state <= idle;
		end else begin
		   next_state <= processing;
		end
	     end // if (strobe_in == 1)	
	   end // case: processing
      endcase // case (state)
   end // always @ (posedge clock)
   
      endmodule // control_cmd

CMD/probador.v
`timescale 1 ns / 1 ps

module probador (new_command, clock, reset, cmd_argument, cmd_index, timeout_enable, serial_ready, ack_in, strobe_in, cmd_in, time_out);

   output           new_command;           //Nuevo procreso del CMD  
   output           clock;                 //Reloj del dispositivo 
   output           reset;                 //Reinicio
   output [31 : 0]  cmd_argument;          //Argumento del comando
   output [5 : 0]   cmd_index;             //Indice del comando
   output 	    timeout_enable;        //Habilitacion del timeout
   output 	    serial_ready;          //Capa fisica lista
   output 	    ack_in;                 //Sincronizacion
   output           strobe_in;             //Fin del uso de la capa fisica 
   output [135 : 0] cmd_in;                //Respuesta recibida
   output 	    time_out;              //Ocurrencia de un timeout

   reg           new_command;
   reg           clock = 0;  
   reg           reset;   
   reg [31 : 0]  cmd_argument;        
   reg [5 : 0]   cmd_index;        
   reg 	         timeout_enable;      
   reg 	         serial_ready;       
   reg 	         ack_in;              
   reg           strobe_in;           
   reg [135 : 0] cmd_in;              
   reg 	         time_out;             


   initial begin
      cmd_index = 6'b011000;
      cmd_argument = 32'hFF99FF88;
      reset = 0;
      timeout_enable = 1;
      time_out = 0;
      cmd_in = 128'hFFFF9999EEEE8888DDDD7777CCCC6666;
      serial_ready = 0;
      new_command = 0;
      strobe_in = 0;
      ack_in = 0;
      
      
     #20 new_command = 1;
     #20 strobe_in = 1;
     #20 ack_in = 1;

     #5 $finish;
   end

   always #1 clock = !clock;

endmodule // probador

CMD/control_interno/testbench.v
module testbench;                                // Se define un modulo de prueba

   wire           new_command;         
   wire           clock;              
   wire           reset;                
   wire [31 : 0]  cmd_argument;       
   wire [5 : 0]   cmd_index;         
   wire 	  timeout_enable;      
   wire 	  serial_ready;       
   wire 	  ack_in;              
   wire           strobe_in;         
   wire [135 : 0] cmd_in;               
   wire 	  time_out;              
   
   wire [127 : 0] response;            
   wire 	  command_complete;    
   wire 	  command_index_error; 
   wire 	  strobe_out;         
   wire 	  ack_out;            
   wire 	  idle_out;            
   wire [39 : 0]  cmd_out; 

  initial begin                             // Bloque que se ejecuta al inicio
     $dumpfile("testbench.vcd");                 // El resultado se guarda en test.vcd
     $dumpvars(0,testbench);
  end
       

  probador valores (new_command, clock, reset, cmd_argument, cmd_index, timeout_enable, serial_ready, ack_in, strobe_in, cmd_in, time_out);

  control_cmd c1 (new_command, clock, reset, cmd_argument, cmd_index, timeout_enable, serial_ready, ack_in, strobe_in, cmd_in, time_out, response, command_complete, command_index_error, strobe_out, ack_out, idle_out, cmd_out);
   

endmodule // test

CMD/control_interno/testbench.vcd
$date
	Wed Nov 30 14:27:22 2016
$end
$version
	Icarus Verilog
$end
$timescale
	1ps
$end
$scope module testbench $end
$var wire 1 ! timeout_enable $end
$var wire 1 " time_out $end
$var wire 1 # strobe_out $end
$var wire 1 $ strobe_in $end
$var wire 1 % serial_ready $end
$var wire 128 & response [127:0] $end
$var wire 1 ' reset $end
$var wire 1 ( new_command $end
$var wire 1 ) idle_out $end
$var wire 1 * command_index_error $end
$var wire 1 + command_complete $end
$var wire 40 , cmd_out [39:0] $end
$var wire 6 - cmd_index [5:0] $end
$var wire 136 . cmd_in [135:0] $end
$var wire 32 / cmd_argument [31:0] $end
$var wire 1 0 clock $end
$var wire 1 1 ack_out $end
$var wire 1 2 ack_in $end
$scope module c1 $end
$var wire 1 ! timeout_enable $end
$var wire 1 " time_out $end
$var wire 1 $ strobe_in $end
$var wire 1 % serial_ready $end
$var wire 1 ' reset $end
$var wire 1 ( new_command $end
$var wire 6 3 cmd_index [5:0] $end
$var wire 136 4 cmd_in [135:0] $end
$var wire 32 5 cmd_argument [31:0] $end
$var wire 1 0 clock $end
$var wire 1 2 ack_in $end
$var reg 1 1 ack_out $end
$var reg 40 6 cmd_out [39:0] $end
$var reg 1 + command_complete $end
$var reg 1 * command_index_error $end
$var reg 1 ) idle_out $end
$var reg 4 7 next_state [3:0] $end
$var reg 128 8 response [127:0] $end
$var reg 4 9 state [3:0] $end
$var reg 1 # strobe_out $end
$upscope $end
$scope module valores $end
$var reg 1 2 ack_in $end
$var reg 1 0 clock $end
$var reg 32 : cmd_argument [31:0] $end
$var reg 136 ; cmd_in [135:0] $end
$var reg 6 < cmd_index [5:0] $end
$var reg 1 ( new_command $end
$var reg 1 ' reset $end
$var reg 1 % serial_ready $end
$var reg 1 $ strobe_in $end
$var reg 1 " time_out $end
$var reg 1 ! timeout_enable $end
$upscope $end
$upscope $end
$enddefinitions $end
#0
$dumpvars
b11000 <
b11111111111111111001100110011001111011101110111010001000100010001101110111011101011101110111011111001100110011000110011001100110 ;
b11111111100110011111111110001000 :
b1 9
b0 8
b10 7
b0 6
b11111111100110011111111110001000 5
b11111111111111111001100110011001111011101110111010001000100010001101110111011101011101110111011111001100110011000110011001100110 4
b11000 3
02
01
00
b11111111100110011111111110001000 /
b11111111111111111001100110011001111011101110111010001000100010001101110111011101011101110111011111001100110011000110011001100110 .
b11000 -
b0 ,
0+
0*
0)
0(
0'
b0 &
0%
0$
0#
0"
1!
$end
#1000
1)
b10 9
10
#2000
00
#3000
10
#4000
00
#5000
10
#6000
00
#7000
10
#8000
00
#9000
10
#10000
00
#11000
10
#12000
00
#13000
10
#14000
00
#15000
10
#16000
00
#17000
10
#18000
00
#19000
10
#20000
b100 7
00
1(
#21000
b1000 7
b101100011111111100110011111111110001000 ,
b101100011111111100110011111111110001000 6
1#
b100 9
10
#22000
00
#23000
b1000 9
10
#24000
00
#25000
10
#26000
00
#27000
10
#28000
00
#29000
10
#30000
00
#31000
10
#32000
00
#33000
10
#34000
00
#35000
10
#36000
00
#37000
10
#38000
00
#39000
10
#40000
b11111111111111111001100110011001111011101110111010001000100010001101110111011101011101110111011111001100110011000110011001100110 &
b11111111111111111001100110011001111011101110111010001000100010001101110111011101011101110111011111001100110011000110011001100110 8
11
1+
00
1$
#41000
10
#42000
00
#43000
10
#44000
00
#45000
10
#46000
00
#47000
10
#48000
00
#49000
10
#50000
00
#51000
10
#52000
00
#53000
10
#54000
00
#55000
10
#56000
00
#57000
10
#58000
00
#59000
10
#60000
b10 7
00
12
#61000
b100 7
b10 9
10
#62000
00
#63000
b1000 7
b100 9
10
#64000
00
#65000
b10 7
b1000 9
10
