CMD/control_interno/control_cmd.v
module control_cmd(new_command, clock, reset, cmd_argument, cmd_index, timeout_enable, ack_in, strobe_in, cmd_in, time_out, response, command_complete, command_index_error, strobe_out, ack_out, idle_out, cmd_out, enable_response, ack_response, enable_command_complete, ack_command_complete);

   
   input           new_command;           //Nuevo procreso del CMD   (WB---Reg)
   input           clock;                 //Reloj del dispositivo 
   input           reset;                 //Reinicio
   input [31 : 0]  cmd_argument;          //Argumento del comando  (Reg)
   input [5 : 0]   cmd_index;             //Indice del comando (Reg)
   input 	   timeout_enable;        //Habilitacion del timeout (Reg)
   input 	   ack_in;                 //Sincronizacion (CF)
   input           strobe_in;             //Fin del uso de la capa fisica (CF) 
   input [127 : 0] cmd_in;                //Respuesta recibida (CF)
   input 	   time_out;              //Ocurrencia de un timeout (CF)
   input	   ack_response;	  // Señal de response leida
   input	   ack_command_complete;  // Señal de command_complete leida
   
   output [127 : 0] response;            //Respuesta escrita a los registros (Reg)
   output 	    command_complete;    //Fin del proceso de CMD  (Reg - WB)
   output 	    command_index_error; //Error de indice comandos (Reg)
   output 	    strobe_out;          //Solicitar el uso a la capa fisica (CF)
   output 	    ack_out;             //Sincronizacion (CF)
   output 	    idle_out;            //Enviar la capa fisica al estado idle (CF)
   output [39 : 0]  cmd_out;             //Parte de la trama por enviar (CF)
   output	    enable_response;	 // habilitar lectura de la señal de response
   output	    enable_command_complete; // habilitar lectura de la señal command_complete

   wire           new_command;         
   wire           clock;              
   wire           reset;                
   wire [31 : 0]  cmd_argument;       
   wire [5 : 0]   cmd_index;         
   wire 	  timeout_enable;            
   wire 	  ack_in;           
   wire           strobe_in;         
   wire [127 : 0] cmd_in;               
   wire 	  time_out;   
   wire		  ack_response;
   wire		  ack_command_complete;           
   
   reg [127 : 0] response;            
   reg 	         command_complete;    
   reg 	         command_index_error; 
   reg 	         strobe_out;         
   reg 	         ack_out;            
   reg 	         idle_out;            
   reg [39 : 0]  cmd_out; 
   reg		 enable_response;
   reg		 enable_command_complete;

   reg [3:0] state = 4'b0001;       
   reg [3:0] next_state;      
   

   //Declaracion de estados
     parameter reset_state = 4'b0001;
     parameter idle = 4'b0010;
     parameter setting_outputs = 4'b0100;
     parameter processing = 4'b1000;

   always @(posedge clock) begin
   	state <= next_state;
   end   


   always @(*) begin

      case (state)

	reset_state :
	  begin
	     response [127 : 0]  <= 128'h00000000000000000000000000000000;
	     command_complete    <= 0;
	     command_index_error <= 0;
	     strobe_out          <= 0;
	     ack_out             <= 0;
	     idle_out            <= 0;
	     cmd_out [39 : 0]    <= 0;
	     enable_response	 <= 0;
	     enable_command_complete <= 0;

	     next_state <= idle;
	     
	  end

	idle :
	  begin
	     if (new_command == 1) begin
		next_state <= setting_outputs;
	     end else begin
		next_state <= idle;
	     end

	     idle_out <= 1;
	     
	  end

	setting_outputs :
	  begin
	     strobe_out <= 1;
	     
	     cmd_out[39] <= 0;
	     cmd_out[38] <= 1;
	     cmd_out[37:32] <= cmd_index[5:0];
	     cmd_out[31:0] <= cmd_argument[31:0];

	     next_state <= processing;
	     
	  end

	processing :
	  begin
	     if (strobe_in == 1) begin
		enable_command_complete <= 1;			// Se habilita el flip-flop para lectura de command_complete
		command_complete <= 1;				// Se pasa el valor de command_complete

		ack_out <= 1;

		enable_response <= 1;				// Se habilita el flip-flop para lectura de response
	        response[127:0] <= cmd_in[127:0];              	// Se pasa a response el contenido de cmd_in
								
	        if (ack_in == 1 && ack_response == 1 && ack_command_complete == 1) begin					
		   next_state <= idle;
		   enable_response <= 0;			// Se deshabilita la lectura de response
		   enable_command_complete <= 0;		// Se deshabilita la lectura de command_complete
		end else begin
		   next_state <= processing;
		end
	     end // if (strobe_in == 1)	
	   end // case: processing
      endcase // case (state)
   end // always @ (posedge clock)
   
      endmodule // control_cmd

CMD/control_interno/probador.v
`timescale 1 ns / 1 ps

module probador (new_command, clock, reset, cmd_argument, cmd_index, timeout_enable, ack_in, strobe_in, cmd_in, time_out, ack_response, ack_command_complete);

   output           new_command;           //Nuevo procreso del CMD  
   output           clock;                 //Reloj del dispositivo 
   output           reset;                 //Reinicio
   output [31 : 0]  cmd_argument;          //Argumento del comando
   output [5 : 0]   cmd_index;             //Indice del comando
   output 	    timeout_enable;        //Habilitacion del timeout
   output 	    ack_in;                 //Sincronizacion
   output           strobe_in;             //Fin del uso de la capa fisica 
   output [127 : 0] cmd_in;                //Respuesta recibida
   output 	    time_out;              //Ocurrencia de un timeout
   output	    ack_response;
   output	    ack_command_complete;

   reg           new_command;
   reg           clock = 0;  
   reg           reset;   
   reg [31 : 0]  cmd_argument;        
   reg [5 : 0]   cmd_index;        
   reg 	         timeout_enable;             
   reg 	         ack_in;              
   reg           strobe_in;           
   reg [127 : 0] cmd_in;              
   reg 	         time_out;             
   reg		 ack_response;
   reg		 ack_command_complete;


   initial begin
      cmd_index = 6'b011000;
      cmd_argument = 32'hFF99FF88;
      reset = 0;
      timeout_enable = 1;
      time_out = 0;
      cmd_in = 128'hFFFF9999EEEE8888DDDD7777CCCC6666;
      new_command = 0;
      strobe_in = 0;
      ack_in = 0;
      
      
     #20 new_command = 1;
     #20 strobe_in = 1;
     #20 ack_response = 1;
     #20 ack_command_complete = 1;
     #20 ack_in = 1;

     #5 $finish;
   end

   always #1 clock = !clock;

endmodule // probador

CMD/control_interno/testbench.v
module testbench;                                // Se define un modulo de prueba

   wire           new_command;         
   wire           clock;              
   wire           reset;                
   wire [31 : 0]  cmd_argument;       
   wire [5 : 0]   cmd_index;         
   wire 	  timeout_enable;            
   wire 	  ack_in;              
   wire           strobe_in;         
   wire [127 : 0] cmd_in;               
   wire 	  time_out;              
   
   wire [127 : 0] response;            
   wire 	  command_complete;    
   wire 	  command_index_error; 
   wire 	  strobe_out;         
   wire 	  ack_out;            
   wire 	  idle_out;            
   wire [39 : 0]  cmd_out;
 
   wire		  enable_response;
   wire		  enable_command_complete;
   wire		  ack_response;
   wire		  ack_command_complete; 

  initial begin                             // Bloque que se ejecuta al inicio
     $dumpfile("testbench.vcd");                 // El resultado se guarda en test.vcd
     $dumpvars(0,testbench);
  end
       

  probador valores (new_command, clock, reset, cmd_argument, cmd_index, timeout_enable, ack_in, strobe_in, cmd_in, time_out, ack_response, ack_command_complete);

  control_cmd c1 (new_command, clock, reset, cmd_argument, cmd_index, timeout_enable, ack_in, strobe_in, cmd_in, time_out, response, command_complete, command_index_error, strobe_out, ack_out, idle_out, cmd_out, enable_response, ack_response, enable_command_complete, ack_command_complete);
   

endmodule // test

CMD/control_interno/testbench.vcd
$date
	Fri Dec  2 08:19:50 2016
$end
$version
	Icarus Verilog
$end
$timescale
	1ps
$end
$scope module testbench $end
$var wire 1 ! timeout_enable $end
$var wire 1 " time_out $end
$var wire 1 # strobe_out $end
$var wire 1 $ strobe_in $end
$var wire 128 % response [127:0] $end
$var wire 1 & reset $end
$var wire 1 ' new_command $end
$var wire 1 ( idle_out $end
$var wire 1 ) enable_response $end
$var wire 1 * enable_command_complete $end
$var wire 1 + command_index_error $end
$var wire 1 , command_complete $end
$var wire 40 - cmd_out [39:0] $end
$var wire 6 . cmd_index [5:0] $end
$var wire 128 / cmd_in [127:0] $end
$var wire 32 0 cmd_argument [31:0] $end
$var wire 1 1 clock $end
$var wire 1 2 ack_response $end
$var wire 1 3 ack_out $end
$var wire 1 4 ack_in $end
$var wire 1 5 ack_command_complete $end
$scope module c1 $end
$var wire 1 ! timeout_enable $end
$var wire 1 " time_out $end
$var wire 1 $ strobe_in $end
$var wire 1 & reset $end
$var wire 1 ' new_command $end
$var wire 6 6 cmd_index [5:0] $end
$var wire 128 7 cmd_in [127:0] $end
$var wire 32 8 cmd_argument [31:0] $end
$var wire 1 1 clock $end
$var wire 1 2 ack_response $end
$var wire 1 4 ack_in $end
$var wire 1 5 ack_command_complete $end
$var reg 1 3 ack_out $end
$var reg 40 9 cmd_out [39:0] $end
$var reg 1 , command_complete $end
$var reg 1 + command_index_error $end
$var reg 1 * enable_command_complete $end
$var reg 1 ) enable_response $end
$var reg 1 ( idle_out $end
$var reg 4 : next_state [3:0] $end
$var reg 128 ; response [127:0] $end
$var reg 4 < state [3:0] $end
$var reg 1 # strobe_out $end
$upscope $end
$scope module valores $end
$var reg 1 5 ack_command_complete $end
$var reg 1 4 ack_in $end
$var reg 1 2 ack_response $end
$var reg 1 1 clock $end
$var reg 32 = cmd_argument [31:0] $end
$var reg 128 > cmd_in [127:0] $end
$var reg 6 ? cmd_index [5:0] $end
$var reg 1 ' new_command $end
$var reg 1 & reset $end
$var reg 1 $ strobe_in $end
$var reg 1 " time_out $end
$var reg 1 ! timeout_enable $end
$upscope $end
$upscope $end
$enddefinitions $end
#0
$dumpvars
b11000 ?
b11111111111111111001100110011001111011101110111010001000100010001101110111011101011101110111011111001100110011000110011001100110 >
b11111111100110011111111110001000 =
b1 <
b0 ;
b10 :
b0 9
b11111111100110011111111110001000 8
b11111111111111111001100110011001111011101110111010001000100010001101110111011101011101110111011111001100110011000110011001100110 7
b11000 6
x5
04
03
x2
01
b11111111100110011111111110001000 0
b11111111111111111001100110011001111011101110111010001000100010001101110111011101011101110111011111001100110011000110011001100110 /
b11000 .
b0 -
0,
0+
0*
0)
0(
0'
0&
b0 %
0$
0#
0"
1!
$end
#1000
1(
b10 <
11
#2000
01
#3000
11
#4000
01
#5000
11
#6000
01
#7000
11
#8000
01
#9000
11
#10000
01
#11000
11
#12000
01
#13000
11
#14000
01
#15000
11
#16000
01
#17000
11
#18000
01
#19000
11
#20000
b100 :
01
1'
#21000
b1000 :
b101100011111111100110011111111110001000 -
b101100011111111100110011111111110001000 9
1#
b100 <
11
#22000
01
#23000
b1000 <
11
#24000
01
#25000
11
#26000
01
#27000
11
#28000
01
#29000
11
#30000
01
#31000
11
#32000
01
#33000
11
#34000
01
#35000
11
#36000
01
#37000
11
#38000
01
#39000
11
#40000
b11111111111111111001100110011001111011101110111010001000100010001101110111011101011101110111011111001100110011000110011001100110 %
b11111111111111111001100110011001111011101110111010001000100010001101110111011101011101110111011111001100110011000110011001100110 ;
1)
13
1,
1*
01
1$
#41000
11
#42000
01
#43000
11
#44000
01
#45000
11
#46000
01
#47000
11
#48000
01
#49000
11
#50000
01
#51000
11
#52000
01
#53000
11
#54000
01
#55000
11
#56000
01
#57000
11
#58000
01
#59000
11
#60000
01
12
#61000
11
#62000
01
#63000
11
#64000
01
#65000
11
#66000
01
#67000
11
#68000
01
#69000
11
#70000
01
#71000
11
#72000
01
#73000
11
#74000
01
#75000
11
#76000
01
#77000
11
#78000
01
#79000
11
#80000
01
15
#81000
11
#82000
01
#83000
11
#84000
01
#85000
11
#86000
01
#87000
11
#88000
01
#89000
11
#90000
01
#91000
11
#92000
01
#93000
11
#94000
01
#95000
11
#96000
01
#97000
11
#98000
01
#99000
11
#100000
0*
0)
b10 :
01
14
#101000
b100 :
b10 <
11
#102000
01
#103000
b1000 :
b100 <
11
#104000
01
#105000
b10 :
0)
0*
b1000 <
11
