CMD/wrapper_paralelo_serial/wrapper_paralelo_serial.v
module wrapper_paralelo_serial (enable, parallel, serial, complete, reset, sd_clock, load_send);
	
	
	input           enable;			// Habilitacion de la carga (CCF)
	input           load_send;		// Enviar (1) cargar (0) (CCF)
	input [n-1 : 0] parallel;		// Trama por enviar (CMD)
	input           reset;
	input           sd_clock;

	output serial;				// Salida serializada (PAD)
	output complete;			// Transmision completa (CCF)

	wire           enable;
	wire           load_send;
	wire [n-1 : 0] parallel;
	wire           reset;
	wire           sd_clock;

	reg serial;
	reg complete;
	reg next_complete;

	integer count = 0;		
	parameter n = 48;
	reg [n-1 : 0] parallel_cargado;


	always @ (posedge sd_clock)
		begin
			if (reset) begin
				serial <= 0;
				parallel_cargado <= 0;
			end else begin
				if (enable) begin
					parallel_cargado <= parallel;
				end else begin
					parallel_cargado <= parallel_cargado;
				end
				if (load_send) begin
					serial <= parallel_cargado [n-1-count];
				end else begin
					 serial <= serial;
				end
			end
		end
	
	always @ (negedge sd_clock)
		begin
			if(reset) begin
				count <= 0;
			end else begin
				if(load_send) begin
					if(count != n-1) begin
						count <= (count + 1);
					end else begin
						count <= 0;
					end 
				end	
			end
		end
	//complete signal generation
	always @ (posedge sd_clock)
		begin
			if (count == n-1) begin
				next_complete = 1'b1;
			end else begin
				next_complete = 1'b0;
			end
		end

	always @ (negedge sd_clock) begin
		complete <= next_complete;
	end

endmodule

CMD/wrapper_paralelo_serial/probador.v
`timescale 1 ns / 1 ps

module probador (parallel, sd_clock, enable, reset, load_send);

	output reg [n-1 : 0] parallel;
	output reg sd_clock;
	output reg enable;
	output reg reset;
	output reg load_send;	           

	parameter n = 48;

   initial begin
      load_send = 0;
      enable = 1;
      reset = 0;
      sd_clock = 0;
      parallel [n-1 : 0] = 48'b11110000_11110000_11110000_11110000_11110000_11110000;

      #3 load_send = 1;

     #100 parallel [n-1 : 0] = 48'b11111111_11111111_11111111_11111111_11111111_11111111;

     #100 $finish;
   end

   always #1 sd_clock = !sd_clock;

endmodule // probador

CMD/wrapper_paralelo_serial/testbench.v
module testbench;  

	parameter n = 48; 

	wire           enable;
	wire [n-1 : 0] parallel;
	wire           reset;
	wire           sd_clock;
	wire           serial;
	wire           complete;
	wire	       load_send;


  initial begin       
     $dumpfile("testbench.vcd");          
     $dumpvars(0,testbench);
  end
       

  probador valores (parallel, sd_clock, enable, reset, load_send);

  wrapper_paralelo_serial c1 (enable, parallel, serial, complete, reset, sd_clock, load_send); 
   

endmodule

CMD/wrapper_paralelo_serial/testbench.vcd
$date
	Mon Nov 28 18:51:37 2016
$end
$version
	Icarus Verilog
$end
$timescale
	1ps
$end
$scope module testbench $end
$var wire 1 ! serial $end
$var wire 1 " sd_clock $end
$var wire 1 # reset $end
$var wire 48 $ parallel [47:0] $end
$var wire 1 % load_send $end
$var wire 1 & enable $end
$var wire 1 ' complete $end
$scope module c1 $end
$var wire 1 " sd_clock $end
$var wire 1 # reset $end
$var wire 48 ( parallel [47:0] $end
$var wire 1 % load_send $end
$var wire 1 & enable $end
$var reg 1 ' complete $end
$var reg 1 ) next_complete $end
$var reg 48 * parallel_cargado [47:0] $end
$var reg 1 ! serial $end
$var integer 32 + count [31:0] $end
$upscope $end
$scope module valores $end
$var reg 1 & enable $end
$var reg 1 % load_send $end
$var reg 48 , parallel [47:0] $end
$var reg 1 # reset $end
$var reg 1 " sd_clock $end
$upscope $end
$upscope $end
$enddefinitions $end
#0
$dumpvars
b111100001111000011110000111100001111000011110000 ,
b0 +
bx *
x)
b111100001111000011110000111100001111000011110000 (
x'
1&
0%
b111100001111000011110000111100001111000011110000 $
0#
0"
x!
$end
#1000
b111100001111000011110000111100001111000011110000 *
0)
1"
#2000
0'
0"
#3000
1!
1"
1%
#4000
b1 +
0"
#5000
1"
#6000
b10 +
0"
#7000
1"
#8000
b11 +
0"
#9000
1"
#10000
b100 +
0"
#11000
0!
1"
#12000
b101 +
0"
#13000
1"
#14000
b110 +
0"
#15000
1"
#16000
b111 +
0"
#17000
1"
#18000
b1000 +
0"
#19000
1!
1"
#20000
b1001 +
0"
#21000
1"
#22000
b1010 +
0"
#23000
1"
#24000
b1011 +
0"
#25000
1"
#26000
b1100 +
0"
#27000
0!
1"
#28000
b1101 +
0"
#29000
1"
#30000
b1110 +
0"
#31000
1"
#32000
b1111 +
0"
#33000
1"
#34000
b10000 +
0"
#35000
1!
1"
#36000
b10001 +
0"
#37000
1"
#38000
b10010 +
0"
#39000
1"
#40000
b10011 +
0"
#41000
1"
#42000
b10100 +
0"
#43000
0!
1"
#44000
b10101 +
0"
#45000
1"
#46000
b10110 +
0"
#47000
1"
#48000
b10111 +
0"
#49000
1"
#50000
b11000 +
0"
#51000
1!
1"
#52000
b11001 +
0"
#53000
1"
#54000
b11010 +
0"
#55000
1"
#56000
b11011 +
0"
#57000
1"
#58000
b11100 +
0"
#59000
0!
1"
#60000
b11101 +
0"
#61000
1"
#62000
b11110 +
0"
#63000
1"
#64000
b11111 +
0"
#65000
1"
#66000
b100000 +
0"
#67000
1!
1"
#68000
b100001 +
0"
#69000
1"
#70000
b100010 +
0"
#71000
1"
#72000
b100011 +
0"
#73000
1"
#74000
b100100 +
0"
#75000
0!
1"
#76000
b100101 +
0"
#77000
1"
#78000
b100110 +
0"
#79000
1"
#80000
b100111 +
0"
#81000
1"
#82000
b101000 +
0"
#83000
1!
1"
#84000
b101001 +
0"
#85000
1"
#86000
b101010 +
0"
#87000
1"
#88000
b101011 +
0"
#89000
1"
#90000
b101100 +
0"
#91000
0!
1"
#92000
b101101 +
0"
#93000
1"
#94000
b101110 +
0"
#95000
1"
#96000
b101111 +
0"
#97000
1)
1"
#98000
b0 +
1'
0"
#99000
1!
0)
1"
#100000
0'
b1 +
0"
#101000
1"
#102000
b10 +
0"
#103000
b111111111111111111111111111111111111111111111111 *
1"
b111111111111111111111111111111111111111111111111 $
b111111111111111111111111111111111111111111111111 (
b111111111111111111111111111111111111111111111111 ,
#104000
b11 +
0"
#105000
1"
#106000
b100 +
0"
#107000
1"
#108000
b101 +
0"
#109000
1"
#110000
b110 +
0"
#111000
1"
#112000
b111 +
0"
#113000
1"
#114000
b1000 +
0"
#115000
1"
#116000
b1001 +
0"
#117000
1"
#118000
b1010 +
0"
#119000
1"
#120000
b1011 +
0"
#121000
1"
#122000
b1100 +
0"
#123000
1"
#124000
b1101 +
0"
#125000
1"
#126000
b1110 +
0"
#127000
1"
#128000
b1111 +
0"
#129000
1"
#130000
b10000 +
0"
#131000
1"
#132000
b10001 +
0"
#133000
1"
#134000
b10010 +
0"
#135000
1"
#136000
b10011 +
0"
#137000
1"
#138000
b10100 +
0"
#139000
1"
#140000
b10101 +
0"
#141000
1"
#142000
b10110 +
0"
#143000
1"
#144000
b10111 +
0"
#145000
1"
#146000
b11000 +
0"
#147000
1"
#148000
b11001 +
0"
#149000
1"
#150000
b11010 +
0"
#151000
1"
#152000
b11011 +
0"
#153000
1"
#154000
b11100 +
0"
#155000
1"
#156000
b11101 +
0"
#157000
1"
#158000
b11110 +
0"
#159000
1"
#160000
b11111 +
0"
#161000
1"
#162000
b100000 +
0"
#163000
1"
#164000
b100001 +
0"
#165000
1"
#166000
b100010 +
0"
#167000
1"
#168000
b100011 +
0"
#169000
1"
#170000
b100100 +
0"
#171000
1"
#172000
b100101 +
0"
#173000
1"
#174000
b100110 +
0"
#175000
1"
#176000
b100111 +
0"
#177000
1"
#178000
b101000 +
0"
#179000
1"
#180000
b101001 +
0"
#181000
1"
#182000
b101010 +
0"
#183000
1"
#184000
b101011 +
0"
#185000
1"
#186000
b101100 +
0"
#187000
1"
#188000
b101101 +
0"
#189000
1"
#190000
b101110 +
0"
#191000
1"
#192000
b101111 +
0"
#193000
1)
1"
#194000
b0 +
1'
0"
#195000
0)
1"
#196000
0'
b1 +
0"
#197000
1"
#198000
b10 +
0"
#199000
1"
#200000
b11 +
0"
#201000
1"
#202000
b100 +
0"
